[
  {
    "ticker": "27FGMF",
    "name": "27four Global Multi-Factor Equity AMETF",
    "volume": "164215.0",
    "price": 12.2,
    "change": 0.07
  },
  {
    "ticker": "27FGSE",
    "name": "27four Global Shariah Equity AMETF",
    "volume": "",
    "price": 10.17,
    "change": NaN
  },
  {
    "ticker": "27FLCE",
    "name": "27four Large Cap Equity AMETF",
    "volume": "",
    "price": 13.98,
    "change": NaN
  },
  {
    "ticker": "27FSMF",
    "name": "27four SA Multi-Factor Equity AMETF",
    "volume": "",
    "price": 12.91,
    "change": NaN
  },
  {
    "ticker": "4SI",
    "name": "4Sight Holdings Limited",
    "volume": "278550.0",
    "price": 0.68,
    "change": -0.02
  },
  {
    "ticker": "ABG",
    "name": "Absa Group Limited",
    "volume": "147922.0",
    "price": 195.53,
    "change": -1.06
  },
  {
    "ticker": "ACL",
    "name": "ArcelorMittal SA Limited",
    "volume": "303150.0",
    "price": 1.3,
    "change": -0.1
  },
  {
    "ticker": "ACS",
    "name": "Acsion Limited",
    "volume": "",
    "price": 8.08,
    "change": NaN
  },
  {
    "ticker": "ACT",
    "name": "AfroCentric Inv Corp Ltd",
    "volume": "",
    "price": 1.28,
    "change": NaN
  },
  {
    "ticker": "ADH",
    "name": "ADvTECH Ltd",
    "volume": "14977.0",
    "price": 34.41,
    "change": -0.09
  },
  {
    "ticker": "ADR",
    "name": "Adcorp Holdings Limited",
    "volume": "5369.0",
    "price": 6.9,
    "change": -0.2
  },
  {
    "ticker": "ADW",
    "name": "African Dawn Capital Ltd",
    "volume": "",
    "price": 0.13,
    "change": NaN
  },
  {
    "ticker": "AEG",
    "name": "Aveng Group Limited",
    "volume": "29250.0",
    "price": 4.58,
    "change": 0.14
  },
  {
    "ticker": "AEL",
    "name": "Altron: Allied Electronics Corporation",
    "volume": "143494.0",
    "price": 17.55,
    "change": 0.01
  },
  {
    "ticker": "AFE",
    "name": "AECI Limited",
    "volume": "14876.0",
    "price": 88.27,
    "change": -0.99
  },
  {
    "ticker": "AFEP",
    "name": "AECI 5.5% Preference Shares",
    "volume": "",
    "price": 14.5,
    "change": NaN
  },
  {
    "ticker": "AFH",
    "name": "Alexander Forbes Grp Hldgs",
    "volume": "864.0",
    "price": 8.28,
    "change": 0.19
  },
  {
    "ticker": "AFT",
    "name": "Afrimat Limited",
    "volume": "251803.0",
    "price": 40.77,
    "change": -1.25
  },
  {
    "ticker": "AGL",
    "name": "Anglo American plc",
    "volume": "140598.0",
    "price": 641.21,
    "change": 11.41
  },
  {
    "ticker": "AIP",
    "name": "Adcock Ingram Hldgs Ltd",
    "volume": "",
    "price": 74.8,
    "change": NaN
  },
  {
    "ticker": "AME",
    "name": "African Media Ent Ltd",
    "volume": "",
    "price": 41.72,
    "change": NaN
  },
  {
    "ticker": "AMIB50",
    "name": "EasyETFs AMI Big50 ETF",
    "volume": "",
    "price": 6.79,
    "change": NaN
  },
  {
    "ticker": "ANG",
    "name": "Anglogold Ashanti Ltd",
    "volume": "93586.0",
    "price": 1177.58,
    "change": 25.98
  },
  {
    "ticker": "ANH",
    "name": "Anheuser-Busch InBev SA/NV",
    "volume": "53229.0",
    "price": 1082.82,
    "change": -8.07
  },
  {
    "ticker": "ANI",
    "name": "Afine Investments Ltd",
    "volume": "",
    "price": 4.93,
    "change": NaN
  },
  {
    "ticker": "AON",
    "name": "African & Overseas Enterprises N-Shares",
    "volume": "",
    "price": 14.15,
    "change": NaN
  },
  {
    "ticker": "AOO",
    "name": "African & Overseas Enterprises Ltd",
    "volume": "",
    "price": 18.81,
    "change": NaN
  },
  {
    "ticker": "AOVP",
    "name": "African & Overseas Ent Preference",
    "volume": "",
    "price": 10.5,
    "change": NaN
  },
  {
    "ticker": "APACXJ",
    "name": "CoreShares All Asia Actively Managed ETF",
    "volume": "12934.0",
    "price": 13.43,
    "change": 0.03
  },
  {
    "ticker": "APF",
    "name": "Accelerate Property Fund Limited",
    "volume": "15000.0",
    "price": 0.48,
    "change": -0.01
  },
  {
    "ticker": "APH",
    "name": "Alphamin Resources Corp",
    "volume": "1862.0",
    "price": 12.51,
    "change": -0.15
  },
  {
    "ticker": "APN",
    "name": "Aspen Pharmacare Holdings",
    "volume": "70864.0",
    "price": 96.7,
    "change": -0.23
  },
  {
    "ticker": "APO",
    "name": "aReit Prop Ltd",
    "volume": "",
    "price": 2.99,
    "change": NaN
  },
  {
    "ticker": "AQUA",
    "name": "AQU Actively Managed ETF",
    "volume": "60.0",
    "price": 11.49,
    "change": -0.02
  },
  {
    "ticker": "ARA",
    "name": "Astoria Investments Ltd",
    "volume": "10798.0",
    "price": 8.16,
    "change": 0.01
  },
  {
    "ticker": "ARI",
    "name": "African Rainbow Min Ltd",
    "volume": "288153.0",
    "price": 169.91,
    "change": 2.9
  },
  {
    "ticker": "ARL",
    "name": "Astral Foods Ltd",
    "volume": "7203.0",
    "price": 221.39,
    "change": -0.91
  },
  {
    "ticker": "ART",
    "name": "Argent Industrial Ltd",
    "volume": "30337.0",
    "price": 28.5,
    "change": 0.1
  },
  {
    "ticker": "ASBI",
    "name": "EasyETFs Africa Bond ETF",
    "volume": "",
    "price": 70.0,
    "change": NaN
  },
  {
    "ticker": "ASC",
    "name": "Ascendis Health Ltd",
    "volume": "413934.0",
    "price": 0.93,
    "change": 0.0
  },
  {
    "ticker": "ASIETF",
    "name": "Arysteq Short-Term Income AMETF",
    "volume": "",
    "price": 9.99,
    "change": NaN
  },
  {
    "ticker": "ATT",
    "name": "Attacq Limited",
    "volume": "88147.0",
    "price": 15.25,
    "change": -0.05
  },
  {
    "ticker": "AVI",
    "name": "AVI Ltd",
    "volume": "50148.0",
    "price": 97.35,
    "change": 0.43
  },
  {
    "ticker": "AXX",
    "name": "Araxi Ltd",
    "volume": "41700.0",
    "price": 1.8,
    "change": 0.0
  },
  {
    "ticker": "BAC",
    "name": "Africa Bitcoin Corporation Ltd",
    "volume": "",
    "price": 11.0,
    "change": NaN
  },
  {
    "ticker": "BACA",
    "name": "Africa Bitcoin Corp Preferred A",
    "volume": "",
    "price": 1.4,
    "change": NaN
  },
  {
    "ticker": "BACB",
    "name": "Africa Bitcoin Corp Preferred B",
    "volume": "",
    "price": 10.89,
    "change": NaN
  },
  {
    "ticker": "BACC",
    "name": "Africa Bitcoin Corp Preferred C",
    "volume": "",
    "price": 2.96,
    "change": NaN
  },
  {
    "ticker": "BAT",
    "name": "Brait SE",
    "volume": "20624.0",
    "price": 2.06,
    "change": 0.0
  },
  {
    "ticker": "BAW",
    "name": "Barloworld Ltd",
    "volume": "2331.0",
    "price": 118.01,
    "change": 0.01
  },
  {
    "ticker": "BAWP",
    "name": "Barworld Ltd 6%Pref",
    "volume": "",
    "price": 0.88,
    "change": NaN
  },
  {
    "ticker": "BCF",
    "name": "Bowler Metcalf Ltd",
    "volume": "10.0",
    "price": 12.91,
    "change": 0.06
  },
  {
    "ticker": "BEL",
    "name": "Bell Equipment Ltd",
    "volume": "",
    "price": 42.97,
    "change": NaN
  },
  {
    "ticker": "BHG",
    "name": "BHP Group",
    "volume": "35609.0",
    "price": 484.81,
    "change": 3.38
  },
  {
    "ticker": "BID",
    "name": "BID Corporation Ltd",
    "volume": "70361.0",
    "price": 426.03,
    "change": -0.94
  },
  {
    "ticker": "BIHLEB",
    "name": "Brait Investment Holdings Ltd",
    "volume": "",
    "price": 850.0,
    "change": NaN
  },
  {
    "ticker": "BIK",
    "name": "Brikor Limited",
    "volume": "",
    "price": 0.12,
    "change": NaN
  },
  {
    "ticker": "BKI",
    "name": "Buka Investments Ltd",
    "volume": "",
    "price": 0.73,
    "change": NaN
  },
  {
    "ticker": "BLU",
    "name": "Blue Label Telecoms Ltd",
    "volume": "569703.0",
    "price": 13.18,
    "change": -0.1
  },
  {
    "ticker": "BOX",
    "name": "Boxer Retail Ltd",
    "volume": "35266.0",
    "price": 74.33,
    "change": -0.67
  },
  {
    "ticker": "BRN",
    "name": "Brimstone Inv Corp Ltd-N",
    "volume": "",
    "price": 4.64,
    "change": NaN
  },
  {
    "ticker": "BRT",
    "name": "Brimstone Inv Corp Ltd",
    "volume": "",
    "price": 5.0,
    "change": NaN
  },
  {
    "ticker": "BSR",
    "name": "Basil Read Holdings Ltd",
    "volume": "",
    "price": 0.04,
    "change": NaN
  },
  {
    "ticker": "BTI",
    "name": "British American Tobacco Plc",
    "volume": "95524.0",
    "price": 940.16,
    "change": 5.36
  },
  {
    "ticker": "BTN",
    "name": "Burstone Group Ltd",
    "volume": "81590.0",
    "price": 9.21,
    "change": 0.02
  },
  {
    "ticker": "BVT",
    "name": "Bidvest Ltd",
    "volume": "97419.0",
    "price": 224.23,
    "change": -0.41
  },
  {
    "ticker": "BWN",
    "name": "Balwin Properties Ltd",
    "volume": "9142.0",
    "price": 2.75,
    "change": 0.03
  },
  {
    "ticker": "BYI",
    "name": "Bytes Technology Group Plc",
    "volume": "5577.0",
    "price": 84.15,
    "change": -0.17
  },
  {
    "ticker": "CAA",
    "name": "CA Sales Holdings Ltd",
    "volume": "687.0",
    "price": 16.14,
    "change": 0.19
  },
  {
    "ticker": "CAC",
    "name": "Cafca Limited",
    "volume": "",
    "price": 3.78,
    "change": NaN
  },
  {
    "ticker": "CAT",
    "name": "Caxton & CTP Publishers Limited",
    "volume": "817.0",
    "price": 13.01,
    "change": -0.49
  },
  {
    "ticker": "CATP",
    "name": "Caxton & CTP 6% Preference Shares",
    "volume": "",
    "price": 90.52,
    "change": NaN
  },
  {
    "ticker": "CCC",
    "name": "Cilo Cybin Holdings Ltd",
    "volume": "",
    "price": 4.5,
    "change": NaN
  },
  {
    "ticker": "CFR",
    "name": "Compagnie Financi\\xc3\\xa8re Richemont",
    "volume": "8698.0",
    "price": 3405.3,
    "change": -11.94
  },
  {
    "ticker": "CGR",
    "name": "Calgro M3 Hldgs Ltd",
    "volume": "",
    "price": 5.23,
    "change": NaN
  },
  {
    "ticker": "CHP",
    "name": "Choppies Enterprises Limited",
    "volume": "6374.0",
    "price": 2.7,
    "change": -0.03
  },
  {
    "ticker": "CKS",
    "name": "Crookes Brothers Ltd",
    "volume": "",
    "price": 25.0,
    "change": NaN
  },
  {
    "ticker": "CLH",
    "name": "City Lodge Hotels Limited",
    "volume": "103707.0",
    "price": 4.15,
    "change": 0.01
  },
  {
    "ticker": "CLI",
    "name": "Clientele Ltd",
    "volume": "",
    "price": 13.09,
    "change": NaN
  },
  {
    "ticker": "CLS",
    "name": "Clicks Group Ltd",
    "volume": "116434.0",
    "price": 352.8,
    "change": -3.02
  },
  {
    "ticker": "CMH",
    "name": "Combined Motor Hldgs Ltd",
    "volume": "",
    "price": 36.0,
    "change": NaN
  },
  {
    "ticker": "CML",
    "name": "Coronation Fund Mngrs Ld",
    "volume": "88598.0",
    "price": 49.63,
    "change": 0.18
  },
  {
    "ticker": "CND",
    "name": "Conduit Capital Limited",
    "volume": "",
    "price": 0.04,
    "change": NaN
  },
  {
    "ticker": "COGCAP",
    "name": "CCP Actively Managed ETF",
    "volume": "",
    "price": 11.26,
    "change": NaN
  },
  {
    "ticker": "COGEM",
    "name": "CGE Actively Managed ETF",
    "volume": "",
    "price": 12.65,
    "change": NaN
  },
  {
    "ticker": "COGES",
    "name": "CES Actively Managed ETF",
    "volume": "",
    "price": 14.96,
    "change": NaN
  },
  {
    "ticker": "COGMAN",
    "name": "CGM Actively Managed ETF",
    "volume": "",
    "price": 13.59,
    "change": NaN
  },
  {
    "ticker": "COGOE",
    "name": "COE Actively Managed ETF",
    "volume": "",
    "price": 12.43,
    "change": NaN
  },
  {
    "ticker": "COH",
    "name": "Curro Holdings Limited",
    "volume": "421656.0",
    "price": 13.57,
    "change": 0.12
  },
  {
    "ticker": "COOPTI",
    "name": "COG Actively Managed ETF",
    "volume": "",
    "price": 13.02,
    "change": NaN
  },
  {
    "ticker": "COUSDI",
    "name": "CDI Actively Managed ETF",
    "volume": "",
    "price": 10.22,
    "change": NaN
  },
  {
    "ticker": "CPI",
    "name": "Capitec Bank Holdings Limited",
    "volume": "54421.0",
    "price": 3955.12,
    "change": 22.2
  },
  {
    "ticker": "CPIP",
    "name": "Capitec Bank Preference Shares",
    "volume": "",
    "price": 108.26,
    "change": NaN
  },
  {
    "ticker": "CPP",
    "name": "Collins Property Group Ltd",
    "volume": "",
    "price": 10.8,
    "change": NaN
  },
  {
    "ticker": "CPR",
    "name": "Copper 360 Ltd",
    "volume": "28000.0",
    "price": 0.69,
    "change": -0.01
  },
  {
    "ticker": "CSB",
    "name": "Cashbuild Limited",
    "volume": "",
    "price": 134.0,
    "change": NaN
  },
  {
    "ticker": "CSGOVI",
    "name": "10X Wealth GOVI Bond ETF",
    "volume": "31433.0",
    "price": 11.61,
    "change": 0.02
  },
  {
    "ticker": "CSP500",
    "name": "10X S&P 500 ETF",
    "volume": "1707.0",
    "price": 118.18,
    "change": 0.13
  },
  {
    "ticker": "CSPROP",
    "name": "10X SA Property Income ETF",
    "volume": "5044.0",
    "price": 15.48,
    "change": 0.02
  },
  {
    "ticker": "CSYSB",
    "name": "10X Yield Selected Bond ETF",
    "volume": "12216.0",
    "price": 12.55,
    "change": -0.01
  },
  {
    "ticker": "CTOP50",
    "name": "10X S&P South Africa Top 50 ETF",
    "volume": "39625.0",
    "price": 43.08,
    "change": 0.38
  },
  {
    "ticker": "CVW",
    "name": "Castleview Property Fund Limited",
    "volume": "",
    "price": 9.54,
    "change": NaN
  },
  {
    "ticker": "DCCUS2",
    "name": "RMB 2YR Dollar Custodial Certificates",
    "volume": "",
    "price": 1761.45,
    "change": NaN
  },
  {
    "ticker": "DCCUSD",
    "name": "RMB Dollar Custodial Certificates",
    "volume": "8.0",
    "price": 1719.3,
    "change": -8.15
  },
  {
    "ticker": "DCP",
    "name": "Dis-Chem Pharmacies Limited",
    "volume": "172517.0",
    "price": 34.51,
    "change": 0.01
  },
  {
    "ticker": "DIB",
    "name": "Dipula Income Fund B",
    "volume": "59961.0",
    "price": 6.4,
    "change": 0.05
  },
  {
    "ticker": "DKR",
    "name": "Deutsche Konsum REIT-AG",
    "volume": "",
    "price": 156.0,
    "change": NaN
  },
  {
    "ticker": "DLT",
    "name": "Delta Property Fund Limited",
    "volume": "266666.0",
    "price": 0.29,
    "change": 0.0
  },
  {
    "ticker": "DNB",
    "name": "Deneb Investments Ltd",
    "volume": "",
    "price": 2.1,
    "change": NaN
  },
  {
    "ticker": "DRD",
    "name": "DRD Gold Ltd",
    "volume": "895762.0",
    "price": 46.69,
    "change": 2.78
  },
  {
    "ticker": "DSBP",
    "name": "Discovery B Preference Shares",
    "volume": "",
    "price": 124.99,
    "change": NaN
  },
  {
    "ticker": "DSY",
    "name": "Discovery Limited",
    "volume": "192725.0",
    "price": 216.4,
    "change": -3.15
  },
  {
    "ticker": "DTC",
    "name": "Datatec Ltd",
    "volume": "60351.0",
    "price": 73.04,
    "change": 0.46
  },
  {
    "ticker": "EASYAI",
    "name": "EasyETFs AI World Actively Managed ETF",
    "volume": "65.0",
    "price": 90.26,
    "change": 1.8
  },
  {
    "ticker": "EASYBF",
    "name": "EasyETFs Balanced Actively Managed ETF",
    "volume": "211.0",
    "price": 13.02,
    "change": 0.06
  },
  {
    "ticker": "EASYGE",
    "name": "EasyETFs Global Equity AMETF",
    "volume": "45107.0",
    "price": 15.51,
    "change": 0.29
  },
  {
    "ticker": "EEL",
    "name": "Efora Energy Limited",
    "volume": "",
    "price": 0.02,
    "change": NaN
  },
  {
    "ticker": "ELI",
    "name": "Ellies Holdings Ltd",
    "volume": "",
    "price": 0.01,
    "change": NaN
  },
  {
    "ticker": "EMH",
    "name": "E Media Holdings Ltd",
    "volume": "",
    "price": 2.15,
    "change": NaN
  },
  {
    "ticker": "EMI",
    "name": "Emira Property Fund Ltd",
    "volume": "366.0",
    "price": 13.6,
    "change": 0.23
  },
  {
    "ticker": "EMN",
    "name": "E Media Holdings Ltd -N-",
    "volume": "36976.0",
    "price": 1.96,
    "change": 0.01
  },
  {
    "ticker": "ENX",
    "name": "enX Group LImited",
    "volume": "",
    "price": 4.01,
    "change": NaN
  },
  {
    "ticker": "EPE",
    "name": "EPE Capital Partners Ltd",
    "volume": "16041.0",
    "price": 7.99,
    "change": 0.13
  },
  {
    "ticker": "EPS",
    "name": "Eastern Platinum Limited",
    "volume": "1000.0",
    "price": 2.61,
    "change": 0.0
  },
  {
    "ticker": "EQU",
    "name": "Equites Prop Fund Ltd",
    "volume": "48556.0",
    "price": 17.0,
    "change": -0.01
  },
  {
    "ticker": "ERN",
    "name": "Erin Energy Corporation",
    "volume": "",
    "price": 30.0,
    "change": NaN
  },
  {
    "ticker": "ETF500",
    "name": "1nvest S&P 500 Index ETF",
    "volume": "39.0",
    "price": 623.3,
    "change": -1.02
  },
  {
    "ticker": "ETF5IT",
    "name": "1nvest S&P 500 IT ETF",
    "volume": "61044.0",
    "price": 36.9,
    "change": -0.14
  },
  {
    "ticker": "ETFBND",
    "name": "1nvest SA Bond ETF",
    "volume": "25.0",
    "price": 117.22,
    "change": 1.04
  },
  {
    "ticker": "ETFEMA",
    "name": "1nvest MSCI EM Asia ETF",
    "volume": "29.0",
    "price": 40.39,
    "change": -0.67
  },
  {
    "ticker": "ETFGGB",
    "name": "1nvest G7 Govt Bond ETF",
    "volume": "95.0",
    "price": 79.22,
    "change": 0.15
  },
  {
    "ticker": "ETFGLD",
    "name": "1nvest Gold ETF",
    "volume": "1072.0",
    "price": 671.9,
    "change": 3.37
  },
  {
    "ticker": "ETFGRE",
    "name": "1nvest Global REIT ETF",
    "volume": "30.0",
    "price": 22.4,
    "change": 0.42
  },
  {
    "ticker": "ETFPLD",
    "name": "1nvest Palladium ETF",
    "volume": "",
    "price": 234.13,
    "change": NaN
  },
  {
    "ticker": "ETFPLT",
    "name": "1nvest Platinum ETF",
    "volume": "42.0",
    "price": 261.25,
    "change": 3.31
  },
  {
    "ticker": "ETFRHO",
    "name": "1nvest Rhodium ETF",
    "volume": "62.0",
    "price": 1294.0,
    "change": 59.91
  },
  {
    "ticker": "ETFSAB",
    "name": "EFB Actively Managed ETF",
    "volume": "",
    "price": 12.11,
    "change": NaN
  },
  {
    "ticker": "ETFSAP",
    "name": "1nvest SA Property ETF",
    "volume": "5323.0",
    "price": 46.84,
    "change": 0.19
  },
  {
    "ticker": "ETFSRI",
    "name": "1nvest MSCI World SRI ETF",
    "volume": "",
    "price": 182.27,
    "change": NaN
  },
  {
    "ticker": "ETFSWX",
    "name": "1nvest SWIX 40 ETF",
    "volume": "24.0",
    "price": 28.5,
    "change": 0.28
  },
  {
    "ticker": "ETFT40",
    "name": "1nvest TOP 40 ETF",
    "volume": "477.0",
    "price": 101.71,
    "change": 0.94
  },
  {
    "ticker": "ETFUSD",
    "name": "1nvest USD Short-Dated ETF",
    "volume": "1.0",
    "price": 17.55,
    "change": 0.23
  },
  {
    "ticker": "ETFWLD",
    "name": "1nvest MSCI World ETF",
    "volume": "14.0",
    "price": 112.31,
    "change": 2.33
  },
  {
    "ticker": "EUZ",
    "name": "Europa Metals Limited",
    "volume": "89694.0",
    "price": 0.45,
    "change": 0.07
  },
  {
    "ticker": "EXP",
    "name": "Exemplar REITail Ltd",
    "volume": "",
    "price": 13.75,
    "change": NaN
  },
  {
    "ticker": "EXX",
    "name": "Exxaro Resources Ltd",
    "volume": "46771.0",
    "price": 187.5,
    "change": -2.0
  },
  {
    "ticker": "FBR",
    "name": "Famous Brands Ltd",
    "volume": "28151.0",
    "price": 53.01,
    "change": -0.81
  },
  {
    "ticker": "FFB",
    "name": "Fortress REIT Ltd",
    "volume": "49190.0",
    "price": 23.61,
    "change": 0.01
  },
  {
    "ticker": "FGL",
    "name": "Finbond Group Ltd",
    "volume": "64209.0",
    "price": 1.44,
    "change": -0.01
  },
  {
    "ticker": "FNB500",
    "name": "FNB S&P 500 Feeder ETF",
    "volume": "",
    "price": 115.84,
    "change": NaN
  },
  {
    "ticker": "FNBEMG",
    "name": "FNB MSCI EM Feeder ETF",
    "volume": "1500.0",
    "price": 75.06,
    "change": 0.38
  },
  {
    "ticker": "FNBEQF",
    "name": "FNB Global 1200 Equity FOF ETF",
    "volume": "30367.0",
    "price": 112.0,
    "change": 2.41
  },
  {
    "ticker": "FNBINF",
    "name": "FNB Government Inflation Bond ETF",
    "volume": "",
    "price": 25.7,
    "change": NaN
  },
  {
    "ticker": "FNBMID",
    "name": "FNB Mid Cap ETF",
    "volume": "1589.0",
    "price": 10.26,
    "change": 0.01
  },
  {
    "ticker": "FNBT40",
    "name": "FNB Top 40 ETF",
    "volume": "28207.0",
    "price": 102.51,
    "change": 0.79
  },
  {
    "ticker": "FNBWDM",
    "name": "FNB MSCI World Feeder ETF",
    "volume": "",
    "price": 21.58,
    "change": NaN
  },
  {
    "ticker": "FNBWGB",
    "name": "FNB World Government Bond ETF",
    "volume": "192.0",
    "price": 7.05,
    "change": 0.04
  },
  {
    "ticker": "FSR",
    "name": "FirstRand Limited",
    "volume": "3360928.0",
    "price": 81.53,
    "change": -0.9
  },
  {
    "ticker": "FTA",
    "name": "Fairvest Ltd A Shares",
    "volume": "",
    "price": 18.5,
    "change": NaN
  },
  {
    "ticker": "FTB",
    "name": "Fairvest Ltd B Shares",
    "volume": "91092.0",
    "price": 6.26,
    "change": 0.02
  },
  {
    "ticker": "FTH",
    "name": "Frontier Transport Holdings",
    "volume": "1949.0",
    "price": 6.93,
    "change": 0.01
  },
  {
    "ticker": "GCT",
    "name": "Greencoat Renewables",
    "volume": "",
    "price": 14.0,
    "change": NaN
  },
  {
    "ticker": "GFI",
    "name": "Gold Fields Ltd",
    "volume": "307156.0",
    "price": 661.6,
    "change": -0.06
  },
  {
    "ticker": "GLD",
    "name": "New Gold Issuer Limited",
    "volume": "5881.0",
    "price": 643.33,
    "change": 3.09
  },
  {
    "ticker": "GLN",
    "name": "Glencore plc",
    "volume": "671857.0",
    "price": 82.24,
    "change": 1.8
  },
  {
    "ticker": "GLOBAL",
    "name": "10X Total World Stock Feeder ETF",
    "volume": "99095.0",
    "price": 17.48,
    "change": 0.09
  },
  {
    "ticker": "GLODIV",
    "name": "10X S&P GlobalDivTrax ETF",
    "volume": "4382.0",
    "price": 19.81,
    "change": -0.05
  },
  {
    "ticker": "GLPROP",
    "name": "10X S&P Global Property ETF",
    "volume": "44.0",
    "price": 46.6,
    "change": -0.34
  },
  {
    "ticker": "GML",
    "name": "Gemfields Group Limited",
    "volume": "",
    "price": 1.29,
    "change": NaN
  },
  {
    "ticker": "GND",
    "name": "Grindrod Ltd",
    "volume": "105882.0",
    "price": 17.1,
    "change": 0.02
  },
  {
    "ticker": "GNDP",
    "name": "Grindrod Ltd Pref",
    "volume": "",
    "price": 100.0,
    "change": NaN
  },
  {
    "ticker": "GPL",
    "name": "Grand Parade Inv Ltd",
    "volume": "",
    "price": 2.04,
    "change": NaN
  },
  {
    "ticker": "GRSP",
    "name": "Goldrush Holdings Ltd",
    "volume": "155000.0",
    "price": 6.0,
    "change": 0.0
  },
  {
    "ticker": "GRT",
    "name": "Growthpoint Properties Limited",
    "volume": "987851.0",
    "price": 16.47,
    "change": 0.01
  },
  {
    "ticker": "GTC",
    "name": "Globe Trade Centre S.A.",
    "volume": "",
    "price": 30.0,
    "change": NaN
  },
  {
    "ticker": "HAR",
    "name": "Harmony GM Co Ltd",
    "volume": "306189.0",
    "price": 282.73,
    "change": 4.53
  },
  {
    "ticker": "HCI",
    "name": "Hosken Consolidated Investments Ltd",
    "volume": "2241.0",
    "price": 132.0,
    "change": -0.29
  },
  {
    "ticker": "HDC",
    "name": "Hudaco Industries Ltd",
    "volume": "309.0",
    "price": 186.03,
    "change": -0.4
  },
  {
    "ticker": "HET",
    "name": "Heriot REIT Limited",
    "volume": "",
    "price": 17.0,
    "change": NaN
  },
  {
    "ticker": "HLM",
    "name": "Hulamin Ltd",
    "volume": "128.0",
    "price": 2.59,
    "change": 0.0
  },
  {
    "ticker": "HMN",
    "name": "Hammerson plc",
    "volume": "5748.0",
    "price": 70.45,
    "change": 1.15
  },
  {
    "ticker": "HUG",
    "name": "Huge Group Ltd",
    "volume": "26504.0",
    "price": 1.4,
    "change": -0.01
  },
  {
    "ticker": "HWA",
    "name": "Hwange Colliery Ltd",
    "volume": "",
    "price": 0.51,
    "change": NaN
  },
  {
    "ticker": "HYP",
    "name": "Hyprop Inv Ltd",
    "volume": "71968.0",
    "price": 51.53,
    "change": -0.07
  },
  {
    "ticker": "IMP",
    "name": "Impala Platinum Hlgs Ltd",
    "volume": "678368.0",
    "price": 185.97,
    "change": 1.73
  },
  {
    "ticker": "INCOME",
    "name": "CoreShares Income Actively Managed ETF",
    "volume": "41950.0",
    "price": 10.6,
    "change": -0.01
  },
  {
    "ticker": "INL",
    "name": "Investec Limited",
    "volume": "67015.0",
    "price": 131.22,
    "change": -1.11
  },
  {
    "ticker": "INP",
    "name": "Investec Plc",
    "volume": "95423.0",
    "price": 131.24,
    "change": -1.07
  },
  {
    "ticker": "INPP",
    "name": "Investec Plc Preference Shares",
    "volume": "",
    "price": 154.0,
    "change": NaN
  },
  {
    "ticker": "INPPR",
    "name": "Investec Plc Preference Shares - Rand",
    "volume": "",
    "price": 87.0,
    "change": NaN
  },
  {
    "ticker": "INPR",
    "name": "Investec Ltd Preference Shares",
    "volume": "",
    "price": 101.0,
    "change": NaN
  },
  {
    "ticker": "IOC",
    "name": "iOCO Ltd",
    "volume": "154553.0",
    "price": 4.15,
    "change": 0.0
  },
  {
    "ticker": "ISA",
    "name": "ISA Holdings Limited",
    "volume": "21060.0",
    "price": 2.03,
    "change": 0.02
  },
  {
    "ticker": "ISB",
    "name": "Insimbi Industrial Holdings",
    "volume": "",
    "price": 0.8,
    "change": NaN
  },
  {
    "ticker": "ISO",
    "name": "ASP Isotopes",
    "volume": "1540.0",
    "price": 150.78,
    "change": 3.78
  },
  {
    "ticker": "ITE",
    "name": "Italtile Ltd",
    "volume": "360.0",
    "price": 9.35,
    "change": 0.24
  },
  {
    "ticker": "IVT",
    "name": "Invicta Holdings Ltd",
    "volume": "700.0",
    "price": 38.24,
    "change": 0.04
  },
  {
    "ticker": "IVTP",
    "name": "Invicta Hldgs Ltd pref",
    "volume": "",
    "price": 110.4,
    "change": NaN
  },
  {
    "ticker": "JBL",
    "name": "Jubilee Metals Group plc",
    "volume": "1500.0",
    "price": 0.7,
    "change": 0.02
  },
  {
    "ticker": "JSE",
    "name": "JSE Ltd",
    "volume": "16865.0",
    "price": 142.18,
    "change": -1.77
  },
  {
    "ticker": "KAL",
    "name": "Kaap Agri Limited",
    "volume": "334.0",
    "price": 45.43,
    "change": -0.44
  },
  {
    "ticker": "KAP",
    "name": "KAP Industrial Holdings Ltd",
    "volume": "187871.0",
    "price": 1.59,
    "change": 0.04
  },
  {
    "ticker": "KBO",
    "name": "Kibo Energy Plc",
    "volume": "",
    "price": 0.01,
    "change": NaN
  },
  {
    "ticker": "KIO",
    "name": "Kumba Iron Ore Ltd",
    "volume": "55273.0",
    "price": 337.13,
    "change": -0.44
  },
  {
    "ticker": "KP2",
    "name": "Kore Potash plc",
    "volume": "1284409.0",
    "price": 0.76,
    "change": 0.0
  },
  {
    "ticker": "KRO",
    "name": "Karooooo Ltd",
    "volume": "1700.0",
    "price": 784.0,
    "change": -11.01
  },
  {
    "ticker": "KST",
    "name": "PSG Konsult Limited",
    "volume": "78921.0",
    "price": 24.67,
    "change": 0.05
  },
  {
    "ticker": "LAB",
    "name": "Labat Africa Ltd",
    "volume": "1213206.0",
    "price": 0.06,
    "change": 0.01
  },
  {
    "ticker": "LBR",
    "name": "Libstar Holdings Ltd",
    "volume": "42772.0",
    "price": 4.63,
    "change": 0.02
  },
  {
    "ticker": "LEW",
    "name": "Lewis Group Ltd",
    "volume": "3450.0",
    "price": 80.01,
    "change": 0.01
  },
  {
    "ticker": "LHC",
    "name": "Life Healthcare Group Holdings",
    "volume": "1094177.0",
    "price": 11.7,
    "change": -0.11
  },
  {
    "ticker": "LSK",
    "name": "Lesaka Technologies",
    "volume": "",
    "price": 75.93,
    "change": NaN
  },
  {
    "ticker": "LTE",
    "name": "Lighthouse Capital Ltd",
    "volume": "3280.0",
    "price": 8.02,
    "change": -0.01
  },
  {
    "ticker": "LUX",
    "name": "Luxe Holdings Limited",
    "volume": "",
    "price": 3.12,
    "change": NaN
  },
  {
    "ticker": "MCG",
    "name": "MultiChoice Group Ltd",
    "volume": "",
    "price": 123.75,
    "change": NaN
  },
  {
    "ticker": "MCZ",
    "name": "MC Mining Limited",
    "volume": "17777.0",
    "price": 2.45,
    "change": 0.25
  },
  {
    "ticker": "MDI",
    "name": "Master Drilling Grp Ltd",
    "volume": "",
    "price": 16.7,
    "change": NaN
  },
  {
    "ticker": "MFL",
    "name": "Metrofile Holdings Ltd",
    "volume": "550000.0",
    "price": 3.13,
    "change": 0.0
  },
  {
    "ticker": "MHB",
    "name": "Mahube Infrastructure Limited",
    "volume": "",
    "price": 6.0,
    "change": NaN
  },
  {
    "ticker": "MKR",
    "name": "Montauk Renewables Inc",
    "volume": "20.0",
    "price": 37.49,
    "change": 4.26
  },
  {
    "ticker": "MMP",
    "name": "Marshall Monteagle plc",
    "volume": "",
    "price": 23.7,
    "change": NaN
  },
  {
    "ticker": "MNP",
    "name": "Mondi plc",
    "volume": "227767.0",
    "price": 191.31,
    "change": 0.09
  },
  {
    "ticker": "MPT",
    "name": "Mpact Limited",
    "volume": "63.0",
    "price": 22.52,
    "change": 0.01
  },
  {
    "ticker": "MRF",
    "name": "Merafe Resources Ltd",
    "volume": "25553.0",
    "price": 1.1,
    "change": -0.01
  },
  {
    "ticker": "MRP",
    "name": "Mr Price Group Ltd",
    "volume": "114399.0",
    "price": 206.11,
    "change": -3.13
  },
  {
    "ticker": "MSP",
    "name": "MAS Real Estate Inc.",
    "volume": "19774.0",
    "price": 21.27,
    "change": -0.36
  },
  {
    "ticker": "MST",
    "name": "Mustek Ltd",
    "volume": "",
    "price": 13.5,
    "change": NaN
  },
  {
    "ticker": "MTA",
    "name": "Metair Investments Ltd",
    "volume": "344.0",
    "price": 6.7,
    "change": 0.12
  },
  {
    "ticker": "MTH",
    "name": "Motus Holdings Ltd",
    "volume": "87784.0",
    "price": 108.61,
    "change": 0.97
  },
  {
    "ticker": "MTM",
    "name": "Momentum Met Hldgs Ltd",
    "volume": "400644.0",
    "price": 33.66,
    "change": -0.08
  },
  {
    "ticker": "MTN",
    "name": "MTN Group Ltd",
    "volume": "861956.0",
    "price": 166.94,
    "change": -3.4
  },
  {
    "ticker": "MTNZF",
    "name": "MTN Zakhele Futhi",
    "volume": "339960.0",
    "price": 4.01,
    "change": -0.44
  },
  {
    "ticker": "MTU",
    "name": "Mantengu Mining Ltd",
    "volume": "6263.0",
    "price": 0.59,
    "change": 0.01
  },
  {
    "ticker": "MUR",
    "name": "Murray & Roberts Holdings",
    "volume": "",
    "price": 1.1,
    "change": NaN
  },
  {
    "ticker": "N91",
    "name": "Ninety One Plc",
    "volume": "91096.0",
    "price": 50.89,
    "change": -0.16
  },
  {
    "ticker": "NCS",
    "name": "Nictus Ltd",
    "volume": "",
    "price": 1.85,
    "change": NaN
  },
  {
    "ticker": "NED",
    "name": "Nedbank Group Limited",
    "volume": "259158.0",
    "price": 241.08,
    "change": 1.54
  },
  {
    "ticker": "NFP",
    "name": "New Frontier Prop Ltd",
    "volume": "",
    "price": 0.05,
    "change": NaN
  },
  {
    "ticker": "NGPLD",
    "name": "NewGold Palladium ETF",
    "volume": "68.0",
    "price": 237.03,
    "change": 1.31
  },
  {
    "ticker": "NGPLT",
    "name": "NewGold Platinum ETF",
    "volume": "518.0",
    "price": 262.57,
    "change": 3.98
  },
  {
    "ticker": "NPH",
    "name": "Northam Platinum Holdings",
    "volume": "556138.0",
    "price": 270.32,
    "change": -3.94
  },
  {
    "ticker": "NPK",
    "name": "Nampak Ltd",
    "volume": "1013.0",
    "price": 495.96,
    "change": 15.95
  },
  {
    "ticker": "NPKP",
    "name": "Nampak Ltd 6%Pref",
    "volume": "",
    "price": 0.7,
    "change": NaN
  },
  {
    "ticker": "NPN",
    "name": "Naspers Ltd",
    "volume": "277595.0",
    "price": 1244.4,
    "change": 11.23
  },
  {
    "ticker": "NPP1",
    "name": "Nampak Ltd 6,5%Pref",
    "volume": "",
    "price": 1.31,
    "change": NaN
  },
  {
    "ticker": "NRL",
    "name": "Newpark REIT Ltd",
    "volume": "",
    "price": 4.8,
    "change": NaN
  },
  {
    "ticker": "NRP",
    "name": "NEPI Rockcastle Plc",
    "volume": "141972.0",
    "price": 139.96,
    "change": -1.27
  },
  {
    "ticker": "NTC",
    "name": "Netcare Limited",
    "volume": "125102.0",
    "price": 14.48,
    "change": -0.23
  },
  {
    "ticker": "NTCP",
    "name": "Netcare Limited Pref",
    "volume": "",
    "price": 95.74,
    "change": NaN
  },
  {
    "ticker": "NTU",
    "name": "Nutun Ltd",
    "volume": "222529.0",
    "price": 0.92,
    "change": -0.01
  },
  {
    "ticker": "NUT",
    "name": "Nutritional Holdings Limited",
    "volume": "",
    "price": 0.01,
    "change": NaN
  },
  {
    "ticker": "NVS",
    "name": "Novus Holdings Limited",
    "volume": "",
    "price": 6.6,
    "change": NaN
  },
  {
    "ticker": "NWL",
    "name": "Nu-World Holdings Limited",
    "volume": "",
    "price": 26.5,
    "change": NaN
  },
  {
    "ticker": "NY1",
    "name": "Ninety One Limited",
    "volume": "54034.0",
    "price": 49.66,
    "change": -0.35
  },
  {
    "ticker": "OAO",
    "name": "Oando Plc",
    "volume": "15000.0",
    "price": 0.28,
    "change": 0.13
  },
  {
    "ticker": "OAS",
    "name": "Oasis Crescent Prop Fund",
    "volume": "",
    "price": 21.0,
    "change": NaN
  },
  {
    "ticker": "OCE",
    "name": "Oceana Group Ltd",
    "volume": "3822.0",
    "price": 49.22,
    "change": -0.17
  },
  {
    "ticker": "OCT",
    "name": "OCTODEC INVEST LTD",
    "volume": "81507.0",
    "price": 12.65,
    "change": 0.05
  },
  {
    "ticker": "OMN",
    "name": "Omnia Holdings Ltd",
    "volume": "15623.0",
    "price": 75.21,
    "change": -0.12
  },
  {
    "ticker": "OMU",
    "name": "Old Mutual Limited",
    "volume": "3396057.0",
    "price": 13.34,
    "change": -0.18
  },
  {
    "ticker": "ORN",
    "name": "Orion Minerals Limited",
    "volume": "1155035.0",
    "price": 0.2,
    "change": 0.0
  },
  {
    "ticker": "OUT",
    "name": "OUTsurance Group Ltd",
    "volume": "570748.0",
    "price": 70.04,
    "change": -0.59
  },
  {
    "ticker": "PAN",
    "name": "Pan African Resource plc",
    "volume": "788230.0",
    "price": 19.54,
    "change": 0.33
  },
  {
    "ticker": "PBG",
    "name": "PBT Group Limited",
    "volume": "",
    "price": 5.88,
    "change": NaN
  },
  {
    "ticker": "PCWGE",
    "name": "Wealth Global Equity CoreSolutions AMETF",
    "volume": "49246.0",
    "price": 10.24,
    "change": -0.12
  },
  {
    "ticker": "PEM",
    "name": "Pembury Lifestyle Grp Lt",
    "volume": "",
    "price": 0.1,
    "change": NaN
  },
  {
    "ticker": "PHP",
    "name": "Primary Health Properties",
    "volume": "122.0",
    "price": 21.56,
    "change": 0.02
  },
  {
    "ticker": "PIK",
    "name": "Pick n Pay Stores Ltd",
    "volume": "207735.0",
    "price": 28.12,
    "change": 0.01
  },
  {
    "ticker": "PIPETF",
    "name": "PIP Actively Managed ETF",
    "volume": "27023.0",
    "price": 10.45,
    "change": -0.02
  },
  {
    "ticker": "PMR",
    "name": "Premier Group Ltd",
    "volume": "13297.0",
    "price": 162.0,
    "change": 0.26
  },
  {
    "ticker": "PMV",
    "name": "Primeserv Group Ltd",
    "volume": "",
    "price": 2.97,
    "change": NaN
  },
  {
    "ticker": "PMXINC",
    "name": "PortfolioMetrix Active Income Prescient AMETF",
    "volume": "20.0",
    "price": 11.37,
    "change": 0.04
  },
  {
    "ticker": "PPC",
    "name": "PPC Limited",
    "volume": "268986.0",
    "price": 5.3,
    "change": 0.01
  },
  {
    "ticker": "PPE",
    "name": "Purple Group Ltd",
    "volume": "53237.0",
    "price": 2.3,
    "change": 0.08
  },
  {
    "ticker": "PPH",
    "name": "Pepkor Holdings Ltd",
    "volume": "3044391.0",
    "price": 26.86,
    "change": 0.07
  },
  {
    "ticker": "PPR",
    "name": "Putprop Ltd",
    "volume": "",
    "price": 4.45,
    "change": NaN
  },
  {
    "ticker": "PREGIP",
    "name": "Prescient Global Income Provider Feeder AMETF",
    "volume": "",
    "price": 9.98,
    "change": NaN
  },
  {
    "ticker": "PRX",
    "name": "Prosus N.V.",
    "volume": "130011.0",
    "price": 1216.01,
    "change": 14.01
  },
  {
    "ticker": "PSV",
    "name": "PSV Holdings Ltd",
    "volume": "",
    "price": 0.08,
    "change": NaN
  },
  {
    "ticker": "PWR",
    "name": "PowerFleet Inc",
    "volume": "",
    "price": 84.86,
    "change": NaN
  },
  {
    "ticker": "QFH",
    "name": "Quantum Foods Hldgs Ltd",
    "volume": "",
    "price": 8.4,
    "change": NaN
  },
  {
    "ticker": "QLT",
    "name": "Quilter Plc",
    "volume": "371941.0",
    "price": 42.02,
    "change": -0.15
  },
  {
    "ticker": "RBO",
    "name": "Rainbow Chicken Ltd",
    "volume": "",
    "price": 4.6,
    "change": NaN
  },
  {
    "ticker": "RBX",
    "name": "Raubex Group Ltd",
    "volume": "348824.0",
    "price": 40.04,
    "change": -1.58
  },
  {
    "ticker": "RCL",
    "name": "RCL Foods Limited",
    "volume": "2589.0",
    "price": 9.74,
    "change": 0.24
  },
  {
    "ticker": "RDF",
    "name": "Redefine Properties Limited",
    "volume": "677939.0",
    "price": 5.57,
    "change": 0.02
  },
  {
    "ticker": "REA",
    "name": "Rebosis Property Fund Ltd A",
    "volume": "",
    "price": 0.96,
    "change": NaN
  },
  {
    "ticker": "REB",
    "name": "Rebosis Property Fund Ltd",
    "volume": "",
    "price": 0.16,
    "change": NaN
  },
  {
    "ticker": "REM",
    "name": "Remgro Ltd",
    "volume": "109856.0",
    "price": 173.0,
    "change": -1.42
  },
  {
    "ticker": "REN",
    "name": "Renergen Limited",
    "volume": "51069.0",
    "price": 12.75,
    "change": 0.25
  },
  {
    "ticker": "RES",
    "name": "Resilient REIT Limited",
    "volume": "116044.0",
    "price": 71.74,
    "change": -0.16
  },
  {
    "ticker": "RFFI",
    "name": "RealFin Fixed Income AMETF",
    "volume": "",
    "price": 10.52,
    "change": NaN
  },
  {
    "ticker": "RFG",
    "name": "RFG Holdings Limited",
    "volume": "83686.0",
    "price": 21.7,
    "change": 0.02
  },
  {
    "ticker": "RHB",
    "name": "RH Bophelo Limited",
    "volume": "",
    "price": 2.25,
    "change": NaN
  },
  {
    "ticker": "RLO",
    "name": "Reunert Ltd",
    "volume": "92352.0",
    "price": 58.27,
    "change": 1.7
  },
  {
    "ticker": "RMH",
    "name": "RMB Holdings Ltd",
    "volume": "219053.0",
    "price": 0.44,
    "change": 0.0
  },
  {
    "ticker": "RNG",
    "name": "Randgold & Exploration Co Ltd",
    "volume": "",
    "price": 0.68,
    "change": NaN
  },
  {
    "ticker": "RNI",
    "name": "Reinet Investments S.C.A",
    "volume": "25491.0",
    "price": 547.25,
    "change": -1.67
  },
  {
    "ticker": "RSG",
    "name": "Resource Generation Ltd",
    "volume": "",
    "price": 0.67,
    "change": NaN
  },
  {
    "ticker": "RTN",
    "name": "Rex Trueform Group -N-",
    "volume": "",
    "price": 12.51,
    "change": NaN
  },
  {
    "ticker": "RTO",
    "name": "Rex Trueform Group Ltd",
    "volume": "",
    "price": 11.21,
    "change": NaN
  },
  {
    "ticker": "RTOP",
    "name": "Rex Trueform Grp 6%Pref",
    "volume": "",
    "price": 1.01,
    "change": NaN
  },
  {
    "ticker": "RWAGP",
    "name": "Reitway Actively Managed ETF",
    "volume": "",
    "price": 10.72,
    "change": NaN
  },
  {
    "ticker": "RWDVF",
    "name": "Reitway Global Property Diversified Prescient ETF",
    "volume": "",
    "price": 11.01,
    "change": NaN
  },
  {
    "ticker": "RWESG",
    "name": "Reitway Global Property ESG Prescient ETF",
    "volume": "",
    "price": 11.21,
    "change": NaN
  },
  {
    "ticker": "RWGPR",
    "name": "Reitway Global Property Prescient ETF",
    "volume": "",
    "price": 11.2,
    "change": NaN
  },
  {
    "ticker": "RWINC",
    "name": "Reitway Global Property Income Prescient ETF",
    "volume": "",
    "price": 9.69,
    "change": NaN
  },
  {
    "ticker": "S32",
    "name": "South32 Limited",
    "volume": "125141.0",
    "price": 34.43,
    "change": 0.2
  },
  {
    "ticker": "SAC",
    "name": "SA Corp Real Estate Ltd",
    "volume": "78998.0",
    "price": 3.24,
    "change": -0.01
  },
  {
    "ticker": "SAP",
    "name": "Sappi Ltd",
    "volume": "2519628.0",
    "price": 24.8,
    "change": 1.78
  },
  {
    "ticker": "SAR",
    "name": "Safari Investments RSA Ltd",
    "volume": "15000.0",
    "price": 8.0,
    "change": 0.1
  },
  {
    "ticker": "SBK",
    "name": "Standard Bank Group Limited",
    "volume": "257021.0",
    "price": 256.64,
    "change": -0.91
  },
  {
    "ticker": "SBKP",
    "name": "Standard Bank 6.5% Preference Shares",
    "volume": "",
    "price": 0.61,
    "change": NaN
  },
  {
    "ticker": "SBP",
    "name": "Sabvest Capital Limited",
    "volume": "",
    "price": 126.19,
    "change": NaN
  },
  {
    "ticker": "SBPP",
    "name": "Standard Bank Preference Shares",
    "volume": "30419.0",
    "price": 100.25,
    "change": 2.01
  },
  {
    "ticker": "SCD",
    "name": "Schroder Eur REIT plc",
    "volume": "",
    "price": 14.67,
    "change": NaN
  },
  {
    "ticker": "SDL",
    "name": "Southern Palladium Ltd",
    "volume": "",
    "price": 13.49,
    "change": NaN
  },
  {
    "ticker": "SDO",
    "name": "Stadio Holdings Limited",
    "volume": "20326.0",
    "price": 10.99,
    "change": 0.09
  },
  {
    "ticker": "SEA",
    "name": "Spear REIT Limited",
    "volume": "96427.0",
    "price": 11.0,
    "change": -0.01
  },
  {
    "ticker": "SEB",
    "name": "Sebata Holdings Limited",
    "volume": "",
    "price": 0.83,
    "change": NaN
  },
  {
    "ticker": "SEP",
    "name": "Sephaku Holdings Limited",
    "volume": "4333.0",
    "price": 1.45,
    "change": -0.05
  },
  {
    "ticker": "SGP",
    "name": "Sail Mining Group Ltd",
    "volume": "",
    "price": 0.06,
    "change": NaN
  },
  {
    "ticker": "SHC",
    "name": "Shaftesbury Capital",
    "volume": "33790.0",
    "price": 32.69,
    "change": 0.24
  },
  {
    "ticker": "SHG",
    "name": "Sea Harvest Group Ltd",
    "volume": "6170.0",
    "price": 8.27,
    "change": 0.19
  },
  {
    "ticker": "SHP",
    "name": "Shoprite Holdings Ltd",
    "volume": "218860.0",
    "price": 289.67,
    "change": 0.57
  },
  {
    "ticker": "SKA",
    "name": "Shuka Minerals",
    "volume": "",
    "price": 1.45,
    "change": NaN
  },
  {
    "ticker": "SLG",
    "name": "Salungano Group Ltd",
    "volume": "",
    "price": 0.5,
    "change": NaN
  },
  {
    "ticker": "SLM",
    "name": "Sanlam Limited",
    "volume": "504601.0",
    "price": 90.64,
    "change": -1.17
  },
  {
    "ticker": "SNT",
    "name": "Santam Limited",
    "volume": "682.0",
    "price": 415.01,
    "change": -1.6
  },
  {
    "ticker": "SNV",
    "name": "Santova Logistics Ltd",
    "volume": "14538.0",
    "price": 7.05,
    "change": 0.0
  },
  {
    "ticker": "SOH",
    "name": "South Ocean Holdings Ltd",
    "volume": "",
    "price": 0.95,
    "change": NaN
  },
  {
    "ticker": "SOL",
    "name": "Sasol Limited",
    "volume": "484799.0",
    "price": 107.46,
    "change": -0.86
  },
  {
    "ticker": "SOLBE1",
    "name": "BEE - Sasol Limited",
    "volume": "",
    "price": 67.0,
    "change": NaN
  },
  {
    "ticker": "SPG",
    "name": "Super Group Ltd",
    "volume": "435202.0",
    "price": 17.02,
    "change": -0.12
  },
  {
    "ticker": "SPP",
    "name": "The Spar Group Ltd",
    "volume": "95057.0",
    "price": 107.97,
    "change": -1.77
  },
  {
    "ticker": "SRE",
    "name": "Sirius Real Estate Ltd",
    "volume": "21889.0",
    "price": 23.19,
    "change": -0.21
  },
  {
    "ticker": "SRI",
    "name": "Supermarket Income REIT",
    "volume": "1.0",
    "price": 18.49,
    "change": 0.38
  },
  {
    "ticker": "SSK",
    "name": "Stefanutti Stocks Holdings Ltd",
    "volume": "6000.0",
    "price": 4.81,
    "change": -0.24
  },
  {
    "ticker": "SSS",
    "name": "Stor-Age Prop REIT Ltd",
    "volume": "265920.0",
    "price": 17.27,
    "change": -0.03
  },
  {
    "ticker": "SSU",
    "name": "Southern Sun Limited",
    "volume": "390559.0",
    "price": 9.0,
    "change": -0.05
  },
  {
    "ticker": "SSW",
    "name": "Sibanye Stillwater Limited",
    "volume": "3055728.0",
    "price": 45.65,
    "change": 1.59
  },
  {
    "ticker": "STX40",
    "name": "Satrix 40 Portfolio",
    "volume": "31650.0",
    "price": 102.55,
    "change": 0.87
  },
  {
    "ticker": "STX500",
    "name": "Satrix S&P 500 Feeder",
    "volume": "31308.0",
    "price": 125.54,
    "change": -0.06
  },
  {
    "ticker": "STXACW",
    "name": "Satrix MSCI ACWI Feeder ETF",
    "volume": "55458.0",
    "price": 93.12,
    "change": 0.2
  },
  {
    "ticker": "STXCAP",
    "name": "Satrix Capped All Share ETF",
    "volume": "1117.0",
    "price": 55.09,
    "change": 0.71
  },
  {
    "ticker": "STXCHN",
    "name": "Satrix MSCI China ETF",
    "volume": "66953.0",
    "price": 56.39,
    "change": 1.21
  },
  {
    "ticker": "STXCTY",
    "name": "Satrix Smart City Infrastructure ETF",
    "volume": "124.0",
    "price": 80.38,
    "change": 0.14
  },
  {
    "ticker": "STXDIV",
    "name": "Satrix DIVI Plus Portfolio",
    "volume": "197428.0",
    "price": 2.81,
    "change": 0.0
  },
  {
    "ticker": "STXEME",
    "name": "Satrix MSCI EM ESG ETF",
    "volume": "26.0",
    "price": 66.7,
    "change": 0.33
  },
  {
    "ticker": "STXEMG",
    "name": "Satrix MSCI EMG Markets",
    "volume": "43277.0",
    "price": 77.14,
    "change": 0.54
  },
  {
    "ticker": "STXESG",
    "name": "Satrix MSCI World ESG ETF",
    "volume": "302.0",
    "price": 93.68,
    "change": -0.31
  },
  {
    "ticker": "STXFIN",
    "name": "Satrix FINI Portfolio",
    "volume": "2908.0",
    "price": 23.17,
    "change": 0.01
  },
  {
    "ticker": "STXGBD",
    "name": "Satrix Global Bond ETF",
    "volume": "25786.0",
    "price": 38.52,
    "change": -0.01
  },
  {
    "ticker": "STXGLB",
    "name": "Satrix Global Balanced Fund of Funds ETF",
    "volume": "",
    "price": 57.5,
    "change": NaN
  },
  {
    "ticker": "STXGOV",
    "name": "Satrix SA Bond Portfolio",
    "volume": "366100.0",
    "price": 9.26,
    "change": 0.09
  },
  {
    "ticker": "STXGVI",
    "name": "Satrix GOVI ETF",
    "volume": "2703.0",
    "price": 83.77,
    "change": 0.89
  },
  {
    "ticker": "STXHLT",
    "name": "Satrix Healthcare Innovation ETF",
    "volume": "",
    "price": 73.82,
    "change": NaN
  },
  {
    "ticker": "STXID",
    "name": "Satrix Inclusion & Diversity ETF",
    "volume": "",
    "price": 39.71,
    "change": NaN
  },
  {
    "ticker": "STXIFR",
    "name": "Satrix Global Infrastructure ETF",
    "volume": "206.0",
    "price": 61.92,
    "change": -0.12
  },
  {
    "ticker": "STXILB",
    "name": "Satrix ILBI Portfolio",
    "volume": "15000.0",
    "price": 8.46,
    "change": 0.05
  },
  {
    "ticker": "STXIND",
    "name": "Satrix INDI Portfolio",
    "volume": "1551.0",
    "price": 140.0,
    "change": 0.74
  },
  {
    "ticker": "STXJGE",
    "name": "Satrix JSE Global Equity ETF",
    "volume": "1206.0",
    "price": 92.9,
    "change": 0.91
  },
  {
    "ticker": "STXLVL",
    "name": "Satrix Low Volume ETF",
    "volume": "",
    "price": 14.41,
    "change": NaN
  },
  {
    "ticker": "STXMMT",
    "name": "Satrix Momentum Portfolio",
    "volume": "4.0",
    "price": 18.46,
    "change": 0.36
  },
  {
    "ticker": "STXNAM",
    "name": "Satrix Namibia Bond ETF",
    "volume": "67906.0",
    "price": 24.95,
    "change": 0.18
  },
  {
    "ticker": "STXNDA",
    "name": "Satrix MSCI India Feeder ETF",
    "volume": "7878.0",
    "price": 83.77,
    "change": -1.08
  },
  {
    "ticker": "STXNDQ",
    "name": "Satrix Nasdaq 100 Prtf",
    "volume": "13617.0",
    "price": 252.34,
    "change": -0.33
  },
  {
    "ticker": "STXPRO",
    "name": "Satrix Property Portfolio",
    "volume": "16207.0",
    "price": 13.36,
    "change": 0.03
  },
  {
    "ticker": "STXQUA",
    "name": "Satrix Quality SA Port",
    "volume": "",
    "price": 10.93,
    "change": NaN
  },
  {
    "ticker": "STXRAF",
    "name": "Satrix RAFI 40 Portfolio",
    "volume": "11.0",
    "price": 32.06,
    "change": 0.46
  },
  {
    "ticker": "STXRES",
    "name": "Satrix RESI ETF Portfolio",
    "volume": "17164.0",
    "price": 109.86,
    "change": 2.72
  },
  {
    "ticker": "STXSHA",
    "name": "Satrix Shariah Top 40 ETF",
    "volume": "6666.0",
    "price": 5.57,
    "change": 0.11
  },
  {
    "ticker": "STXSWX",
    "name": "Satrix SWIX Top 40 Portfolio",
    "volume": "180.0",
    "price": 19.14,
    "change": 0.19
  },
  {
    "ticker": "STXTRA",
    "name": "Satrix Traci 3-Month ETF",
    "volume": "1622.0",
    "price": 37.35,
    "change": -0.09
  },
  {
    "ticker": "STXVEQ",
    "name": "Satrix Value Equity ETF",
    "volume": "",
    "price": 18.35,
    "change": NaN
  },
  {
    "ticker": "STXWDM",
    "name": "Satrix MSCI World Feeder",
    "volume": "34357.0",
    "price": 110.88,
    "change": 0.02
  },
  {
    "ticker": "STXWIS",
    "name": "Satrix MSCI World Islamic Feeder ETF",
    "volume": "",
    "price": 49.57,
    "change": NaN
  },
  {
    "ticker": "SUI",
    "name": "Sun International Ltd",
    "volume": "117887.0",
    "price": 38.58,
    "change": 0.08
  },
  {
    "ticker": "SUR",
    "name": "Spur Corporation Ltd",
    "volume": "13722.0",
    "price": 36.65,
    "change": -0.35
  },
  {
    "ticker": "SXM",
    "name": "Sable Exploration & Mining Ltd",
    "volume": "",
    "price": 0.06,
    "change": NaN
  },
  {
    "ticker": "SYFANG",
    "name": "Sygnia Itrix FANG.AI Actively Managed ETF",
    "volume": "42863.0",
    "price": 19.97,
    "change": 0.08
  },
  {
    "ticker": "SYG",
    "name": "Sygnia Limited",
    "volume": "164.0",
    "price": 33.34,
    "change": 0.0
  },
  {
    "ticker": "SYG4IR",
    "name": "Sygnia Itrix 4th IR Global Equity ETF",
    "volume": "1606.0",
    "price": 59.47,
    "change": -0.13
  },
  {
    "ticker": "SYG500",
    "name": "Sygnia Itrix S&P 500 ETF",
    "volume": "4805.0",
    "price": 119.08,
    "change": 0.0
  },
  {
    "ticker": "SYGCN",
    "name": "Sygnia Itrix New China Sectors ETF",
    "volume": "157.0",
    "price": 38.58,
    "change": 0.79
  },
  {
    "ticker": "SYGEMF",
    "name": "Sygnia Itrix MSCI EM 50 ETF",
    "volume": "3412.0",
    "price": 25.05,
    "change": 0.15
  },
  {
    "ticker": "SYGESG",
    "name": "Sygnia Itrix S&P Global 1200 ESG ETF",
    "volume": "10.0",
    "price": 63.27,
    "change": 0.06
  },
  {
    "ticker": "SYGEU",
    "name": "Sygnia Itrix EURO STOXX 50 ETF",
    "volume": "2651.0",
    "price": 115.0,
    "change": 0.24
  },
  {
    "ticker": "SYGH",
    "name": "Sygnia Itrix SOL H150 ETF",
    "volume": "",
    "price": 30.01,
    "change": NaN
  },
  {
    "ticker": "SYGJP",
    "name": "Sygnia Itrix MSCI Japan ETF",
    "volume": "70901.0",
    "price": 23.26,
    "change": 0.12
  },
  {
    "ticker": "SYGP",
    "name": "Sygnia Itrix Global Property ETF",
    "volume": "",
    "price": 49.36,
    "change": NaN
  },
  {
    "ticker": "SYGT40",
    "name": "Sygnia Itrix Top 40 ETF",
    "volume": "1070.0",
    "price": 103.74,
    "change": 1.01
  },
  {
    "ticker": "SYGUK",
    "name": "Sygnia Itrix FTSE 100 ETF",
    "volume": "31.0",
    "price": 222.0,
    "change": 0.57
  },
  {
    "ticker": "SYGUS",
    "name": "Sygnia Itrix MSCI US ETF",
    "volume": "3224.0",
    "price": 110.42,
    "change": -0.53
  },
  {
    "ticker": "SYGWD",
    "name": "Sygnia Itrix MSCI World Index ETF",
    "volume": "19710.0",
    "price": 75.87,
    "change": 0.2
  },
  {
    "ticker": "SZK",
    "name": "SAB Zenzele Kabili",
    "volume": "",
    "price": 35.9,
    "change": NaN
  },
  {
    "ticker": "TBIGTF",
    "name": "TBI Global Targeted Yield UCITS Fund",
    "volume": "",
    "price": 100.6,
    "change": NaN
  },
  {
    "ticker": "TBIMAI",
    "name": "TBI Global Multi-Asset Income Fund",
    "volume": "",
    "price": 100.87,
    "change": NaN
  },
  {
    "ticker": "TBS",
    "name": "Tiger Brands Ltd",
    "volume": "36347.0",
    "price": 326.53,
    "change": -3.47
  },
  {
    "ticker": "TEX",
    "name": "Texton Property Fund Limited",
    "volume": "",
    "price": 2.65,
    "change": NaN
  },
  {
    "ticker": "TFG",
    "name": "Foschini Group Limited",
    "volume": "317306.0",
    "price": 90.42,
    "change": -0.5
  },
  {
    "ticker": "TFGP",
    "name": "Foschini Ltd 6.5% Preference Share",
    "volume": "",
    "price": 1.01,
    "change": NaN
  },
  {
    "ticker": "TGA",
    "name": "Thungela Resources Ltd",
    "volume": "48564.0",
    "price": 78.74,
    "change": 0.84
  },
  {
    "ticker": "THA",
    "name": "Tharisa plc",
    "volume": "1230.0",
    "price": 22.11,
    "change": 0.01
  },
  {
    "ticker": "TKG",
    "name": "Telkom SA SOC Ltd",
    "volume": "466270.0",
    "price": 46.87,
    "change": -0.06
  },
  {
    "ticker": "TLM",
    "name": "Telemaster Holdings Limited",
    "volume": "",
    "price": 0.99,
    "change": NaN
  },
  {
    "ticker": "TMT",
    "name": "Trematon Capital Inv Ltd",
    "volume": "2000.0",
    "price": 1.15,
    "change": -0.04
  },
  {
    "ticker": "TON",
    "name": "Tongaat Hulett Ltd",
    "volume": "",
    "price": 4.04,
    "change": NaN
  },
  {
    "ticker": "TPC",
    "name": "Transpaco Ltd",
    "volume": "16784.0",
    "price": 35.2,
    "change": 1.1
  },
  {
    "ticker": "TRL",
    "name": "Trellidor Hldgs Ltd",
    "volume": "94664.0",
    "price": 1.76,
    "change": -0.02
  },
  {
    "ticker": "TRU",
    "name": "Truworths Int Ltd",
    "volume": "1286205.0",
    "price": 52.31,
    "change": -0.67
  },
  {
    "ticker": "TSG",
    "name": "Tsogo Sun Gaming Ltd",
    "volume": "24482.0",
    "price": 6.94,
    "change": -0.06
  },
  {
    "ticker": "TTO",
    "name": "Trustco Group Holdings Ltd",
    "volume": "",
    "price": 0.3,
    "change": NaN
  },
  {
    "ticker": "UAT",
    "name": "Union Atlantic Minerals Ltd",
    "volume": "",
    "price": 0.04,
    "change": NaN
  },
  {
    "ticker": "UPL",
    "name": "Universal Partners Ltd",
    "volume": "",
    "price": 17.9,
    "change": NaN
  },
  {
    "ticker": "VAL",
    "name": "Valterra Platinum Ltd",
    "volume": "173200.0",
    "price": 1062.99,
    "change": 29.99
  },
  {
    "ticker": "VIS",
    "name": "Visual International Holdings",
    "volume": "",
    "price": 0.03,
    "change": NaN
  },
  {
    "ticker": "VKE",
    "name": "Vukile Property Fund Ltd",
    "volume": "157985.0",
    "price": 22.88,
    "change": -0.07
  },
  {
    "ticker": "VOD",
    "name": "Vodacom Group Ltd",
    "volume": "794958.0",
    "price": 137.51,
    "change": 1.74
  },
  {
    "ticker": "VUN",
    "name": "Vunani Ltd",
    "volume": "2029.0",
    "price": 1.95,
    "change": -0.05
  },
  {
    "ticker": "VUNGLE",
    "name": "VGE Actively Managed ETF",
    "volume": "",
    "price": 10.93,
    "change": NaN
  },
  {
    "ticker": "WBC",
    "name": "WeBuyCars Holdings Ltd",
    "volume": "192020.0",
    "price": 44.13,
    "change": -0.72
  },
  {
    "ticker": "WBO",
    "name": "Wilson Bayly Hlm-Ovc Ltd",
    "volume": "18220.0",
    "price": 147.26,
    "change": -2.21
  },
  {
    "ticker": "WEZ",
    "name": "Wesizwe Platinum Ltd",
    "volume": "",
    "price": 0.45,
    "change": NaN
  },
  {
    "ticker": "WHL",
    "name": "Woolworths Holdings Ltd",
    "volume": "326341.0",
    "price": 53.11,
    "change": 0.09
  },
  {
    "ticker": "WNXT40",
    "name": "10X Wealth Next 40 Equal Weighted ETF",
    "volume": "3203.0",
    "price": 12.28,
    "change": -0.07
  },
  {
    "ticker": "WTOP20",
    "name": "10X Wealth Top 20 Capped ETF",
    "volume": "4546.0",
    "price": 14.76,
    "change": 0.08
  },
  {
    "ticker": "WVR",
    "name": "Weaver Fintech Ltd",
    "volume": "",
    "price": 51.0,
    "change": NaN
  },
  {
    "ticker": "XII",
    "name": "Numeral Ltd",
    "volume": "600000.0",
    "price": 0.02,
    "change": 0.0
  },
  {
    "ticker": "YRK",
    "name": "York Timber Holdings Ltd",
    "volume": "",
    "price": 2.21,
    "change": NaN
  },
  {
    "ticker": "YYLBEE",
    "name": "YeboYethu (RF) Ltd",
    "volume": "2470.0",
    "price": 40.0,
    "change": 0.0
  },
  {
    "ticker": "ZED",
    "name": "Zeder Investments Limited",
    "volume": "55622.0",
    "price": 1.27,
    "change": -0.02
  },
  {
    "ticker": "ZZD",
    "name": "Zeda Limited",
    "volume": "3000.0",
    "price": 12.1,
    "change": -0.01
  }
]