[
  {
    "ticker": "ABBEYBDS",
    "name": "Abbey Mortgage Bank Plc",
    "volume": "5600.0",
    "price": 6.5,
    "change": 0.0
  },
  {
    "ticker": "ABCTRANS",
    "name": "Associated Bus Company",
    "volume": "557153.0",
    "price": 3.44,
    "change": -0.38
  },
  {
    "ticker": "ACADEMY",
    "name": "Academy Press",
    "volume": "47193.0",
    "price": 6.7,
    "change": 0.0
  },
  {
    "ticker": "ACCESSCORP",
    "name": "Access Holdings Plc",
    "volume": "54611005.0",
    "price": 21.8,
    "change": -0.2
  },
  {
    "ticker": "AFRINSURE",
    "name": "African Alliance Insurance",
    "volume": "",
    "price": 0.2,
    "change": NaN
  },
  {
    "ticker": "AFRIPRUD",
    "name": "Africa Prudential Plc",
    "volume": "556611.0",
    "price": 14.0,
    "change": 0.0
  },
  {
    "ticker": "AFROMEDIA",
    "name": "Afromedia Plc",
    "volume": "",
    "price": 0.24,
    "change": NaN
  },
  {
    "ticker": "AIICO",
    "name": "Aiico Insurance Plc",
    "volume": "6365337.0",
    "price": 3.45,
    "change": -0.04
  },
  {
    "ticker": "AIRTELAFRI",
    "name": "Airtel Africa Plc",
    "volume": "8092.0",
    "price": 2270.0,
    "change": 0.0
  },
  {
    "ticker": "ALEX",
    "name": "Aluminium Extrusion Industries",
    "volume": "676.0",
    "price": 7.15,
    "change": 0.0
  },
  {
    "ticker": "ARADEL",
    "name": "Aradel Holdings",
    "volume": "1850511.0",
    "price": 700.0,
    "change": -6.0
  },
  {
    "ticker": "ASOSAVINGS",
    "name": "Aso Savings & Loans",
    "volume": "",
    "price": 1.07,
    "change": NaN
  },
  {
    "ticker": "AUSTINLAZ",
    "name": "Austin Laz & Company",
    "volume": "273847.0",
    "price": 2.36,
    "change": 0.0
  },
  {
    "ticker": "AVAIF",
    "name": "Ava Infrastructure Fund",
    "volume": "",
    "price": 1000000.0,
    "change": NaN
  },
  {
    "ticker": "BAPLC",
    "name": "Briclinks Africa Plc",
    "volume": "",
    "price": 6.25,
    "change": NaN
  },
  {
    "ticker": "BERGER",
    "name": "Berger Paints",
    "volume": "90333.0",
    "price": 37.0,
    "change": 0.0
  },
  {
    "ticker": "BETAGLAS",
    "name": "Beta Glass Company",
    "volume": "213213.0",
    "price": 370.0,
    "change": 0.0
  },
  {
    "ticker": "BUACEMENT",
    "name": "BUA Cement Plc",
    "volume": "599272.0",
    "price": 168.0,
    "change": 0.0
  },
  {
    "ticker": "BUAFOODS",
    "name": "BUA Foods",
    "volume": "247639.0",
    "price": 692.5,
    "change": 0.0
  },
  {
    "ticker": "CADBURY",
    "name": "Cadbury Nigeria",
    "volume": "104789.0",
    "price": 58.95,
    "change": 0.0
  },
  {
    "ticker": "CAP",
    "name": "CAP Plc",
    "volume": "12648.0",
    "price": 73.0,
    "change": 0.0
  },
  {
    "ticker": "CAVERTON",
    "name": "Caverton Offshore Support Group",
    "volume": "3815086.0",
    "price": 5.55,
    "change": 0.4
  },
  {
    "ticker": "CHAMPION",
    "name": "Champion Breweries",
    "volume": "7121391.0",
    "price": 13.7,
    "change": -0.65
  },
  {
    "ticker": "CHAMS",
    "name": "Chams Plc",
    "volume": "2291483.0",
    "price": 3.12,
    "change": -0.08
  },
  {
    "ticker": "CHELLARAM",
    "name": "Chellarams Plc",
    "volume": "19973.0",
    "price": 16.25,
    "change": 0.0
  },
  {
    "ticker": "CILEASING",
    "name": "C&I Leasing Plc",
    "volume": "286699.0",
    "price": 5.36,
    "change": 0.06
  },
  {
    "ticker": "CNIF",
    "name": "Coronation Infrastructure Fund",
    "volume": "778.0",
    "price": 100.0,
    "change": 0.0
  },
  {
    "ticker": "CONHALLPLC",
    "name": "Consolidated Hallmark Holdings",
    "volume": "30641946.0",
    "price": 4.0,
    "change": -0.16
  },
  {
    "ticker": "CONOIL",
    "name": "Conoil Plc",
    "volume": "19049.0",
    "price": 190.7,
    "change": 0.0
  },
  {
    "ticker": "CORNERST",
    "name": "Cornerstone Insurance Company",
    "volume": "225552.0",
    "price": 6.1,
    "change": 0.0
  },
  {
    "ticker": "CUSTODIAN",
    "name": "Custodian & Allied Plc",
    "volume": "1036353.0",
    "price": 39.9,
    "change": 0.0
  },
  {
    "ticker": "CUTIX",
    "name": "Cutix Plc",
    "volume": "2400313.0",
    "price": 3.38,
    "change": -0.02
  },
  {
    "ticker": "CWG",
    "name": "Computer Warehouse Group",
    "volume": "303423.0",
    "price": 16.95,
    "change": 0.0
  },
  {
    "ticker": "DAARCOMM",
    "name": "Daar Communications",
    "volume": "94589.0",
    "price": 0.95,
    "change": 0.0
  },
  {
    "ticker": "DANGCEM",
    "name": "Dangote Cement",
    "volume": "235638.0",
    "price": 534.6,
    "change": 0.0
  },
  {
    "ticker": "DANGSUGAR",
    "name": "Dangote Sugar Refinery",
    "volume": "1355281.0",
    "price": 56.0,
    "change": -2.0
  },
  {
    "ticker": "DEAPCAP",
    "name": "Deap Capital Management & Trust",
    "volume": "550089.0",
    "price": 1.74,
    "change": 0.02
  },
  {
    "ticker": "DUNLOP",
    "name": "DN Tyre & Rubber Plc",
    "volume": "",
    "price": 0.2,
    "change": NaN
  },
  {
    "ticker": "EKOCORP",
    "name": "Ekocorp Plc",
    "volume": "",
    "price": 5.8,
    "change": NaN
  },
  {
    "ticker": "ELLAHLAKES",
    "name": "Ellah Lakes Plc",
    "volume": "9829400.0",
    "price": 12.6,
    "change": -0.2
  },
  {
    "ticker": "ENAMELWA",
    "name": "Nigerian Enamelware Plc",
    "volume": "",
    "price": 40.5,
    "change": NaN
  },
  {
    "ticker": "ETERNA",
    "name": "Eterna Plc",
    "volume": "80721.0",
    "price": 35.5,
    "change": 0.0
  },
  {
    "ticker": "ETI",
    "name": "Ecobank Transnational Inc",
    "volume": "225705.0",
    "price": 34.65,
    "change": 0.0
  },
  {
    "ticker": "ETRANZACT",
    "name": "E-Tranzact International",
    "volume": "198329.0",
    "price": 13.25,
    "change": 0.0
  },
  {
    "ticker": "EUNISELL",
    "name": "Eunisell Interlinked Plc",
    "volume": "94348.0",
    "price": 79.0,
    "change": 0.0
  },
  {
    "ticker": "FCMB",
    "name": "FCMB Group Plc",
    "volume": "5271266.0",
    "price": 10.3,
    "change": -0.3
  },
  {
    "ticker": "FIDELITYBK",
    "name": "Fidelity Bank Plc",
    "volume": "8715492.0",
    "price": 19.15,
    "change": 0.0
  },
  {
    "ticker": "FIDSON",
    "name": "Fidson Healthcare",
    "volume": "595046.0",
    "price": 40.0,
    "change": 0.0
  },
  {
    "ticker": "FIRSTHOLDCO",
    "name": "First HoldCo Plc",
    "volume": "1571693.0",
    "price": 30.05,
    "change": -0.1
  },
  {
    "ticker": "FTGINSURE",
    "name": "Fortis Global Insurance",
    "volume": "",
    "price": 0.2,
    "change": NaN
  },
  {
    "ticker": "FTNCOCOA",
    "name": "FTN Cocoa Processors",
    "volume": "246367.0",
    "price": 5.27,
    "change": 0.0
  },
  {
    "ticker": "GEREGU",
    "name": "Geregu Power Plc",
    "volume": "938.0",
    "price": 1141.5,
    "change": 0.0
  },
  {
    "ticker": "GOLDBREW",
    "name": "Golden Guinea Breweries",
    "volume": "",
    "price": 7.1,
    "change": NaN
  },
  {
    "ticker": "GTCO",
    "name": "Guaranty Trust Holding",
    "volume": "11907860.0",
    "price": 84.9,
    "change": -0.9
  },
  {
    "ticker": "GUINEAINS",
    "name": "Guinea Insurance",
    "volume": "406200.0",
    "price": 1.2,
    "change": -0.08
  },
  {
    "ticker": "GUINNESS",
    "name": "Guinness Nigeria",
    "volume": "383854.0",
    "price": 167.0,
    "change": -3.0
  },
  {
    "ticker": "HMCALL",
    "name": "Haldane McCall",
    "volume": "1648258.0",
    "price": 4.25,
    "change": 0.05
  },
  {
    "ticker": "HONYFLOUR",
    "name": "Honeywell Flour Mill",
    "volume": "1205695.0",
    "price": 18.45,
    "change": -1.45
  },
  {
    "ticker": "IKEJAHOTEL",
    "name": "Ikeja Hotel Plc",
    "volume": "523558.0",
    "price": 20.5,
    "change": 0.0
  },
  {
    "ticker": "IMG",
    "name": "Industrial & Medical Gases",
    "volume": "22262.0",
    "price": 32.4,
    "change": 0.0
  },
  {
    "ticker": "INFINITY",
    "name": "Infinity Trust Mortgage Bank",
    "volume": "2.0",
    "price": 7.0,
    "change": 0.0
  },
  {
    "ticker": "INTBREW",
    "name": "International Breweries",
    "volume": "235360.0",
    "price": 11.95,
    "change": 0.0
  },
  {
    "ticker": "INTENEGINS",
    "name": "International Energy Insurance",
    "volume": "297477.0",
    "price": 2.45,
    "change": -0.27
  },
  {
    "ticker": "JAIZBANK",
    "name": "Jaiz Bank Plc",
    "volume": "1696093.0",
    "price": 4.5,
    "change": -0.18
  },
  {
    "ticker": "JAPAULGOLD",
    "name": "Japaul Gold and Ventures Plc",
    "volume": "51703538.0",
    "price": 2.2,
    "change": -0.03
  },
  {
    "ticker": "JBERGER",
    "name": "Julius Berger Nigeria Plc",
    "volume": "146870.0",
    "price": 138.2,
    "change": 0.0
  },
  {
    "ticker": "JOHNHOLT",
    "name": "John Holt Plc",
    "volume": "23735.0",
    "price": 5.4,
    "change": 0.0
  },
  {
    "ticker": "JULI",
    "name": "Juli Plc",
    "volume": "2346.0",
    "price": 8.06,
    "change": 0.0
  },
  {
    "ticker": "LASACO",
    "name": "Lasaco Assurance",
    "volume": "10453411.0",
    "price": 2.65,
    "change": -0.01
  },
  {
    "ticker": "LEARNAFRCA",
    "name": "Learn Africa",
    "volume": "89261.0",
    "price": 5.85,
    "change": 0.0
  },
  {
    "ticker": "LEGENDINT",
    "name": "Legend Internet",
    "volume": "342892.0",
    "price": 6.05,
    "change": 0.0
  },
  {
    "ticker": "LINKASSURE",
    "name": "Linkage Assurance",
    "volume": "6960301.0",
    "price": 1.99,
    "change": 0.14
  },
  {
    "ticker": "LIVESTOCK",
    "name": "Livestock Feeds",
    "volume": "352704.0",
    "price": 6.55,
    "change": 0.0
  },
  {
    "ticker": "LIVINGTRUST",
    "name": "LivingTrust Mortgage Bank",
    "volume": "1563421.0",
    "price": 3.73,
    "change": 0.0
  },
  {
    "ticker": "MANSARD",
    "name": "AXA Mansard Insurance",
    "volume": "513975.0",
    "price": 13.0,
    "change": 0.0
  },
  {
    "ticker": "MAYBAKER",
    "name": "May & Baker Nigeria",
    "volume": "1348316.0",
    "price": 15.8,
    "change": -1.75
  },
  {
    "ticker": "MBENEFIT",
    "name": "Mutual Benefits Assurance",
    "volume": "3214662.0",
    "price": 3.36,
    "change": -0.02
  },
  {
    "ticker": "MCNICHOLS",
    "name": "McNichols Plc",
    "volume": "1282996.0",
    "price": 2.72,
    "change": -0.01
  },
  {
    "ticker": "MECURE",
    "name": "MeCure Industries",
    "volume": "9656.0",
    "price": 27.7,
    "change": 0.0
  },
  {
    "ticker": "MEYER",
    "name": "Meyer Plc",
    "volume": "17499.0",
    "price": 16.15,
    "change": 0.0
  },
  {
    "ticker": "MOFIREIF",
    "name": "MOFI Real Estate Investment Fund",
    "volume": "",
    "price": 100.0,
    "change": NaN
  },
  {
    "ticker": "MORISON",
    "name": "Morison Industries",
    "volume": "27389.0",
    "price": 3.22,
    "change": 0.0
  },
  {
    "ticker": "MTNN",
    "name": "MTN Nigeria",
    "volume": "365605.0",
    "price": 475.0,
    "change": 0.0
  },
  {
    "ticker": "MULTITREX",
    "name": "Multi-Trex Integrated Foods",
    "volume": "",
    "price": 0.36,
    "change": NaN
  },
  {
    "ticker": "MULTIVERSE",
    "name": "Multiverse Mining & Exploration",
    "volume": "9180.0",
    "price": 10.05,
    "change": 0.0
  },
  {
    "ticker": "NAHCO",
    "name": "Nigerian Aviation Handling Co.",
    "volume": "386534.0",
    "price": 109.9,
    "change": 0.0
  },
  {
    "ticker": "NASCON",
    "name": "National Salt Company",
    "volume": "38643.0",
    "price": 103.6,
    "change": 0.0
  },
  {
    "ticker": "NB",
    "name": "Nigerian Breweries",
    "volume": "277025.0",
    "price": 70.0,
    "change": 0.0
  },
  {
    "ticker": "NCR",
    "name": "NCR Nigeria",
    "volume": "163051.0",
    "price": 30.95,
    "change": 0.0
  },
  {
    "ticker": "NEIMETH",
    "name": "Neimeth International Pharma",
    "volume": "432336.0",
    "price": 5.6,
    "change": 0.0
  },
  {
    "ticker": "NEM",
    "name": "N.E.M. Insurance Company",
    "volume": "1114941.0",
    "price": 29.05,
    "change": -0.75
  },
  {
    "ticker": "NESTLE",
    "name": "Nestle Nigeria",
    "volume": "99466.0",
    "price": 1730.0,
    "change": 0.0
  },
  {
    "ticker": "NGXGROUP",
    "name": "Nigerian Exchange Group",
    "volume": "266349.0",
    "price": 51.6,
    "change": 0.0
  },
  {
    "ticker": "NIDF",
    "name": "Nigeria Infrastructure Debt Fund",
    "volume": "65957.0",
    "price": 115.0,
    "change": 0.0
  },
  {
    "ticker": "NNFM",
    "name": "Northern Nigeria Flour Mills",
    "volume": "4186.0",
    "price": 84.3,
    "change": 0.0
  },
  {
    "ticker": "NPFMCRFBK",
    "name": "NPF Microfinance Bank",
    "volume": "844744.0",
    "price": 2.93,
    "change": -0.06
  },
  {
    "ticker": "NSLTECH",
    "name": "Secure Electronic Technology",
    "volume": "1254628.0",
    "price": 0.85,
    "change": 0.0
  },
  {
    "ticker": "OANDO",
    "name": "Oando Plc",
    "volume": "1438298.0",
    "price": 40.95,
    "change": -0.95
  },
  {
    "ticker": "OKOMUOIL",
    "name": "Okomu Oil Palm",
    "volume": "97629.0",
    "price": 1110.0,
    "change": 0.0
  },
  {
    "ticker": "OMATEK",
    "name": "Omatek Ventures",
    "volume": "226471.0",
    "price": 1.3,
    "change": 0.0
  },
  {
    "ticker": "PHARMDEKO",
    "name": "Pharma-Deko Plc",
    "volume": "",
    "price": 1.83,
    "change": NaN
  },
  {
    "ticker": "PREMPAINTS",
    "name": "Premier Paints",
    "volume": "",
    "price": 10.0,
    "change": NaN
  },
  {
    "ticker": "PRESCO",
    "name": "Presco Plc",
    "volume": "46546.0",
    "price": 1450.0,
    "change": 0.0
  },
  {
    "ticker": "PRESTIGE",
    "name": "Prestige Assurance Company",
    "volume": "1124407.0",
    "price": 1.57,
    "change": -0.03
  },
  {
    "ticker": "PZ",
    "name": "PZ Cussons Nigeria",
    "volume": "522968.0",
    "price": 39.6,
    "change": 0.0
  },
  {
    "ticker": "REDSTAREX",
    "name": "Red Star Express Plc",
    "volume": "180215.0",
    "price": 9.2,
    "change": 0.0
  },
  {
    "ticker": "REGALINS",
    "name": "Regency Alliance Insurance",
    "volume": "1221316.0",
    "price": 1.14,
    "change": 0.0
  },
  {
    "ticker": "RONCHESS",
    "name": "Ronchess Global Resources",
    "volume": "",
    "price": 81.0,
    "change": NaN
  },
  {
    "ticker": "ROYALEX",
    "name": "Royal Exchange",
    "volume": "898783.0",
    "price": 1.98,
    "change": -0.07
  },
  {
    "ticker": "RTBRISCOE",
    "name": "RT Briscoe",
    "volume": "88950.0",
    "price": 3.38,
    "change": 0.0
  },
  {
    "ticker": "SCOA",
    "name": "SCOA Nigeria",
    "volume": "60193.0",
    "price": 7.1,
    "change": 0.0
  },
  {
    "ticker": "SEPLAT",
    "name": "Seplat Petroleum Development Co.",
    "volume": "7506.0",
    "price": 5809.0,
    "change": 0.0
  },
  {
    "ticker": "SFSREIT",
    "name": "Skye Shelter Fund Plc",
    "volume": "27409.0",
    "price": 418.75,
    "change": 0.0
  },
  {
    "ticker": "SKYAVN",
    "name": "Skyway Aviation Handling Co. Plc",
    "volume": "50283.0",
    "price": 80.6,
    "change": 0.0
  },
  {
    "ticker": "SOVRENINS",
    "name": "Sovereign Trust Insurance",
    "volume": "2730752.0",
    "price": 3.12,
    "change": -0.28
  },
  {
    "ticker": "STACO",
    "name": "Standard Trust Assurance",
    "volume": "",
    "price": 0.48,
    "change": NaN
  },
  {
    "ticker": "STANBIC",
    "name": "Stanbic IBTC Holdings",
    "volume": "212207.0",
    "price": 105.0,
    "change": 0.0
  },
  {
    "ticker": "STERLINGNG",
    "name": "Sterling Bank",
    "volume": "14296480.0",
    "price": 7.5,
    "change": 0.05
  },
  {
    "ticker": "SUNUASSUR",
    "name": "Sunu Assurances Nigeria Plc",
    "volume": "61030.0",
    "price": 4.6,
    "change": 0.0
  },
  {
    "ticker": "TANTALIZER",
    "name": "Tantalizers Plc",
    "volume": "65111751.0",
    "price": 2.6,
    "change": 0.02
  },
  {
    "ticker": "THOMASWY",
    "name": "Thomas Wyatt Nigeria",
    "volume": "",
    "price": 2.75,
    "change": NaN
  },
  {
    "ticker": "TIP",
    "name": "The Initiates Plc",
    "volume": "3169775.0",
    "price": 11.1,
    "change": -0.55
  },
  {
    "ticker": "TOTAL",
    "name": "Total Nigeria",
    "volume": "1629.0",
    "price": 640.0,
    "change": 0.0
  },
  {
    "ticker": "TRANSCOHOT",
    "name": "Transcorp Hotels Plc",
    "volume": "4387.0",
    "price": 174.9,
    "change": 0.0
  },
  {
    "ticker": "TRANSCORP",
    "name": "Transcorp Nigeria",
    "volume": "926486.0",
    "price": 42.0,
    "change": -3.0
  },
  {
    "ticker": "TRANSEXPR",
    "name": "Trans-Nationwide Express",
    "volume": "21509.0",
    "price": 2.15,
    "change": 0.0
  },
  {
    "ticker": "TRANSPOWER",
    "name": "Transcorp Power",
    "volume": "8058.0",
    "price": 307.8,
    "change": 0.0
  },
  {
    "ticker": "TRIPPLEG",
    "name": "Tripple Gee & Co. Plc",
    "volume": "115455.0",
    "price": 4.42,
    "change": 0.0
  },
  {
    "ticker": "UACN",
    "name": "UAC of Nigeria",
    "volume": "1802475.0",
    "price": 68.3,
    "change": 5.25
  },
  {
    "ticker": "UBA",
    "name": "United Bank for Africa",
    "volume": "3901662.0",
    "price": 38.4,
    "change": -0.5
  },
  {
    "ticker": "UCAP",
    "name": "United Capital Plc",
    "volume": "1981447.0",
    "price": 17.2,
    "change": -0.15
  },
  {
    "ticker": "UHOMREIT",
    "name": "Union Homes Real Estate Inv.",
    "volume": "12122.0",
    "price": 51.85,
    "change": 0.0
  },
  {
    "ticker": "UNILEVER",
    "name": "Unilever Nigeria",
    "volume": "92028.0",
    "price": 73.0,
    "change": 0.0
  },
  {
    "ticker": "UNIONDICON",
    "name": "Union Dicon Salt",
    "volume": "708449.0",
    "price": 7.0,
    "change": 0.1
  },
  {
    "ticker": "UNITYBNK",
    "name": "Unity Bank",
    "volume": "",
    "price": 1.51,
    "change": NaN
  },
  {
    "ticker": "UNIVINSURE",
    "name": "Universal Insurance Company",
    "volume": "4272826.0",
    "price": 1.17,
    "change": -0.13
  },
  {
    "ticker": "UPDC",
    "name": "UPDC Plc",
    "volume": "681744.0",
    "price": 5.96,
    "change": 0.0
  },
  {
    "ticker": "UPDCREIT",
    "name": "UPDC Real Estate Investment Trust",
    "volume": "1277650.0",
    "price": 6.8,
    "change": 0.0
  },
  {
    "ticker": "UPL",
    "name": "University Press",
    "volume": "1311794.0",
    "price": 6.0,
    "change": 0.4
  },
  {
    "ticker": "VANLEER",
    "name": "Greif Nigeria",
    "volume": "",
    "price": 5.45,
    "change": NaN
  },
  {
    "ticker": "VERITASKAP",
    "name": "Veritas Kapital Assurance Plc",
    "volume": "1704173.0",
    "price": 1.8,
    "change": -0.05
  },
  {
    "ticker": "VFDGROUP",
    "name": "VFD Group",
    "volume": "2233125.0",
    "price": 10.45,
    "change": 0.0
  },
  {
    "ticker": "VITAFOAM",
    "name": "Vitafoam Nigeria",
    "volume": "273002.0",
    "price": 87.0,
    "change": 0.0
  },
  {
    "ticker": "WAPCO",
    "name": "Lafarge Wapco",
    "volume": "238232.0",
    "price": 134.0,
    "change": 0.0
  },
  {
    "ticker": "WAPIC",
    "name": "Wapic Insurance",
    "volume": "445673.0",
    "price": 2.8,
    "change": -0.01
  },
  {
    "ticker": "WEMABANK",
    "name": "Wema Bank",
    "volume": "1634619.0",
    "price": 19.7,
    "change": -0.1
  },
  {
    "ticker": "ZENITHBANK",
    "name": "Zenith Bank Plc",
    "volume": "30817492.0",
    "price": 60.0,
    "change": -1.0
  }
]