[
  {
    "ticker": "ABSA",
    "name": "Absa Bank Kenya Plc",
    "volume": "23466.0",
    "price": 26.0,
    "change": 0.15
  },
  {
    "ticker": "AMAC",
    "name": "Africa Mega Agricorp",
    "volume": "",
    "price": 65.25,
    "change": NaN
  },
  {
    "ticker": "ARM",
    "name": "ARM Cement Limited",
    "volume": "",
    "price": 5.55,
    "change": NaN
  },
  {
    "ticker": "BAMB",
    "name": "Bamburi Cement Limited",
    "volume": "",
    "price": 47.2,
    "change": NaN
  },
  {
    "ticker": "BAT",
    "name": "British American Tobacco Kenya",
    "volume": "364.0",
    "price": 441.25,
    "change": -8.75
  },
  {
    "ticker": "BKG",
    "name": "BK Group Plc",
    "volume": "49.0",
    "price": 42.5,
    "change": -0.3
  },
  {
    "ticker": "BOC",
    "name": "BOC Kenya Limited",
    "volume": "40.0",
    "price": 126.0,
    "change": -3.75
  },
  {
    "ticker": "BRIT",
    "name": "Britam Holdings Limited",
    "volume": "20850.0",
    "price": 9.0,
    "change": 0.2
  },
  {
    "ticker": "CABL",
    "name": "East African Cables Limited",
    "volume": "",
    "price": 1.0,
    "change": NaN
  },
  {
    "ticker": "CARB",
    "name": "Carbacid Investments Limited",
    "volume": "159323.0",
    "price": 31.0,
    "change": 0.35
  },
  {
    "ticker": "CGEN",
    "name": "Car and General Kenya Limited",
    "volume": "5949.0",
    "price": 57.0,
    "change": -1.25
  },
  {
    "ticker": "CIC",
    "name": "CIC Insurance Group Limited",
    "volume": "92350.0",
    "price": 4.8,
    "change": 0.01
  },
  {
    "ticker": "COOP",
    "name": "Co-operative Bank of Kenya Limited",
    "volume": "102335.0",
    "price": 23.0,
    "change": 0.1
  },
  {
    "ticker": "CRWN",
    "name": "Crown Paints Kenya Limited",
    "volume": "2.0",
    "price": 55.5,
    "change": -4.5
  },
  {
    "ticker": "CTUM",
    "name": "Centum Investment Company",
    "volume": "8376.0",
    "price": 16.2,
    "change": -0.2
  },
  {
    "ticker": "DCON",
    "name": "Deacons East Africa Plc",
    "volume": "",
    "price": 0.45,
    "change": NaN
  },
  {
    "ticker": "DTK",
    "name": "Diamond Trust Bank Kenya Limited",
    "volume": "2096.0",
    "price": 115.25,
    "change": 0.0
  },
  {
    "ticker": "EABL",
    "name": "East African Breweries Limited",
    "volume": "231.0",
    "price": 247.0,
    "change": 1.75
  },
  {
    "ticker": "EGAD",
    "name": "Eaagads Limited",
    "volume": "7.0",
    "price": 20.5,
    "change": 0.35
  },
  {
    "ticker": "EQTY",
    "name": "Equity Group Holdings Limited",
    "volume": "9242.0",
    "price": 69.5,
    "change": -0.25
  },
  {
    "ticker": "EVRD",
    "name": "Eveready East Africa Limited",
    "volume": "3245.0",
    "price": 1.3,
    "change": -0.02
  },
  {
    "ticker": "FTGH",
    "name": "Flame Tree Group Holdings Limited",
    "volume": "4328.0",
    "price": 1.8,
    "change": -0.01
  },
  {
    "ticker": "GLD",
    "name": "Absa NewGold ETF",
    "volume": "103.0",
    "price": 5200.0,
    "change": 220.0
  },
  {
    "ticker": "HAFR",
    "name": "Home Afrika Limited",
    "volume": "18961.0",
    "price": 1.19,
    "change": 0.03
  },
  {
    "ticker": "HBE",
    "name": "Homeboyz Entertainment",
    "volume": "",
    "price": 4.66,
    "change": NaN
  },
  {
    "ticker": "HFCK",
    "name": "HF Group Limited",
    "volume": "9526.0",
    "price": 10.75,
    "change": -0.1
  },
  {
    "ticker": "IMH",
    "name": "I&M Holdings Plc",
    "volume": "49490.0",
    "price": 46.0,
    "change": 0.05
  },
  {
    "ticker": "JUB",
    "name": "Jubilee Holdings Limited",
    "volume": "25570.0",
    "price": 325.0,
    "change": 1.25
  },
  {
    "ticker": "KAPC",
    "name": "Kapchorua Tea Company Limited",
    "volume": "540.0",
    "price": 203.0,
    "change": -7.25
  },
  {
    "ticker": "KCB",
    "name": "KCB Group",
    "volume": "29800.0",
    "price": 70.0,
    "change": 0.0
  },
  {
    "ticker": "KEGN",
    "name": "KenGen Plc",
    "volume": "420338.0",
    "price": 10.5,
    "change": 0.0
  },
  {
    "ticker": "KNRE",
    "name": "Kenya Re-Insurance Corporation Ltd",
    "volume": "1141752.0",
    "price": 3.24,
    "change": 0.03
  },
  {
    "ticker": "KPLC",
    "name": "Kenya Power & Lighting Company",
    "volume": "661761.0",
    "price": 14.4,
    "change": 0.0
  },
  {
    "ticker": "KPLC-P4",
    "name": "Kenya Power 4% Preference Shares",
    "volume": "",
    "price": 4.51,
    "change": NaN
  },
  {
    "ticker": "KPLC-P7",
    "name": "Kenya Power 7% Preference Shares",
    "volume": "",
    "price": 6.0,
    "change": NaN
  },
  {
    "ticker": "KQ",
    "name": "Kenya Airways Limited",
    "volume": "42133.0",
    "price": 3.81,
    "change": 0.04
  },
  {
    "ticker": "KUKZ",
    "name": "Kakuzi Limited",
    "volume": "74.0",
    "price": 400.0,
    "change": -0.25
  },
  {
    "ticker": "KURV",
    "name": "Kurwitu Ventures Limited",
    "volume": "",
    "price": 1500.0,
    "change": NaN
  },
  {
    "ticker": "LAPR",
    "name": "Laptrust Imara Income-REIT",
    "volume": "",
    "price": 20.0,
    "change": NaN
  },
  {
    "ticker": "LBTY",
    "name": "Liberty Kenya Holdings Limited",
    "volume": "3070.0",
    "price": 10.45,
    "change": 0.0
  },
  {
    "ticker": "LIMT",
    "name": "Limuru Tea Company Limited",
    "volume": "",
    "price": 423.5,
    "change": NaN
  },
  {
    "ticker": "LKL",
    "name": "Longhorn Publishers Limited",
    "volume": "1092.0",
    "price": 2.9,
    "change": -0.02
  },
  {
    "ticker": "MSC",
    "name": "Mumias Sugar Company Limited",
    "volume": "",
    "price": 0.28,
    "change": NaN
  },
  {
    "ticker": "NBV",
    "name": "Nairobi Business Ventures Ltd",
    "volume": "94130.0",
    "price": 1.5,
    "change": 0.0
  },
  {
    "ticker": "NCBA",
    "name": "NCBA Group Plc",
    "volume": "4630.0",
    "price": 87.0,
    "change": 2.0
  },
  {
    "ticker": "NMG",
    "name": "Nation Media Group",
    "volume": "140.0",
    "price": 13.5,
    "change": 0.5
  },
  {
    "ticker": "NSE",
    "name": "Nairobi Securities Exchange Limited",
    "volume": "36630.0",
    "price": 20.95,
    "change": 0.3
  },
  {
    "ticker": "OCH",
    "name": "Olympia Capital Holdings Limited",
    "volume": "118.0",
    "price": 7.5,
    "change": 0.0
  },
  {
    "ticker": "PORT",
    "name": "East African Portland Cement Co. Ltd",
    "volume": "21.0",
    "price": 58.75,
    "change": -1.75
  },
  {
    "ticker": "SASN",
    "name": "Sasini Tea and Coffee Limited",
    "volume": "3555.0",
    "price": 18.9,
    "change": -0.1
  },
  {
    "ticker": "SBIC",
    "name": "Stanbic Holdings Limited",
    "volume": "6495.0",
    "price": 195.0,
    "change": 0.25
  },
  {
    "ticker": "SCAN",
    "name": "ScanGroup Limited",
    "volume": "1791.0",
    "price": 2.6,
    "change": -0.16
  },
  {
    "ticker": "SCBK",
    "name": "Standard Chartered Bank Limited",
    "volume": "574.0",
    "price": 310.0,
    "change": -1.5
  },
  {
    "ticker": "SCOM",
    "name": "Safaricom Plc",
    "volume": "82455.0",
    "price": 29.5,
    "change": 0.0
  },
  {
    "ticker": "SGL",
    "name": "Standard Group Limited",
    "volume": "2086.0",
    "price": 6.44,
    "change": 0.42
  },
  {
    "ticker": "SKL",
    "name": "Shri Krishana Overseas Ltd",
    "volume": "2050.0",
    "price": 7.48,
    "change": 0.0
  },
  {
    "ticker": "SLAM",
    "name": "Sanlam Kenya Plc",
    "volume": "137.0",
    "price": 8.5,
    "change": -0.36
  },
  {
    "ticker": "SMER",
    "name": "Sameer Africa Plc",
    "volume": "1403.0",
    "price": 14.8,
    "change": -0.15
  },
  {
    "ticker": "SMWF",
    "name": "Satrix MSCI World Feeder ETF",
    "volume": "10.0",
    "price": 849.0,
    "change": 3.0
  },
  {
    "ticker": "TCL",
    "name": "Trans Century Limited",
    "volume": "",
    "price": 0.71,
    "change": NaN
  },
  {
    "ticker": "TOTL",
    "name": "Total Kenya Limited",
    "volume": "2238.0",
    "price": 44.0,
    "change": -0.85
  },
  {
    "ticker": "TPSE",
    "name": "TPS Eastern Africa Serena Limited",
    "volume": "22.0",
    "price": 17.0,
    "change": 0.0
  },
  {
    "ticker": "UCHM",
    "name": "Uchumi Supermarket Limited",
    "volume": "14002.0",
    "price": 0.38,
    "change": -0.01
  },
  {
    "ticker": "UMME",
    "name": "Umeme Limited",
    "volume": "17827.0",
    "price": 7.6,
    "change": 0.04
  },
  {
    "ticker": "UNGA",
    "name": "Unga Group Limited",
    "volume": "342.0",
    "price": 22.5,
    "change": -1.95
  },
  {
    "ticker": "WTK",
    "name": "Williamson Tea Kenya Limited",
    "volume": "127.0",
    "price": 168.0,
    "change": 3.25
  },
  {
    "ticker": "XPRS",
    "name": "Express Kenya Limited",
    "volume": "420.0",
    "price": 7.28,
    "change": 0.34
  }
]