[
  {
    "ticker": "ABSA",
    "name": "Absa Bank Kenya Plc",
    "volume": "178888.0",
    "price": 22.9,
    "change": 0.1
  },
  {
    "ticker": "AMAC",
    "name": "Africa Mega Agricorp",
    "volume": "",
    "price": 65.0,
    "change": NaN
  },
  {
    "ticker": "ARM",
    "name": "ARM Cement Limited",
    "volume": "",
    "price": 5.55,
    "change": NaN
  },
  {
    "ticker": "BAMB",
    "name": "Bamburi Cement Limited",
    "volume": "",
    "price": 47.2,
    "change": NaN
  },
  {
    "ticker": "BAT",
    "name": "British American Tobacco Kenya",
    "volume": "923.0",
    "price": 445.0,
    "change": -0.75
  },
  {
    "ticker": "BKG",
    "name": "BK Group Plc",
    "volume": "1124.0",
    "price": 42.65,
    "change": 0.35
  },
  {
    "ticker": "BOC",
    "name": "BOC Kenya Limited",
    "volume": "79.0",
    "price": 131.0,
    "change": 2.0
  },
  {
    "ticker": "BRIT",
    "name": "Britam Holdings Limited",
    "volume": "399486.0",
    "price": 8.7,
    "change": 0.18
  },
  {
    "ticker": "CABL",
    "name": "East African Cables Limited",
    "volume": "",
    "price": 1.0,
    "change": NaN
  },
  {
    "ticker": "CARB",
    "name": "Carbacid Investments Limited",
    "volume": "11034.0",
    "price": 26.7,
    "change": -0.05
  },
  {
    "ticker": "CGEN",
    "name": "Car and General Kenya Limited",
    "volume": "12320.0",
    "price": 54.0,
    "change": 1.0
  },
  {
    "ticker": "CIC",
    "name": "CIC Insurance Group Limited",
    "volume": "165751.0",
    "price": 4.78,
    "change": 0.17
  },
  {
    "ticker": "COOP",
    "name": "Co-operative Bank of Kenya Limited",
    "volume": "140219.0",
    "price": 20.8,
    "change": 0.1
  },
  {
    "ticker": "CRWN",
    "name": "Crown Paints Kenya Limited",
    "volume": "2035.0",
    "price": 50.0,
    "change": -4.5
  },
  {
    "ticker": "CTUM",
    "name": "Centum Investment Company",
    "volume": "4393.0",
    "price": 14.65,
    "change": 0.0
  },
  {
    "ticker": "DCON",
    "name": "Deacons East Africa Plc",
    "volume": "",
    "price": 0.45,
    "change": NaN
  },
  {
    "ticker": "DTK",
    "name": "Diamond Trust Bank Kenya Limited",
    "volume": "11036.0",
    "price": 105.0,
    "change": 0.0
  },
  {
    "ticker": "EABL",
    "name": "East African Breweries Limited",
    "volume": "58525.0",
    "price": 230.0,
    "change": 6.0
  },
  {
    "ticker": "EGAD",
    "name": "Eaagads Limited",
    "volume": "410.0",
    "price": 20.0,
    "change": 0.25
  },
  {
    "ticker": "EQTY",
    "name": "Equity Group Holdings Limited",
    "volume": "448998.0",
    "price": 60.5,
    "change": 0.5
  },
  {
    "ticker": "EVRD",
    "name": "Eveready East Africa Limited",
    "volume": "13347.0",
    "price": 1.37,
    "change": 0.03
  },
  {
    "ticker": "FTGH",
    "name": "Flame Tree Group Holdings Limited",
    "volume": "145200.0",
    "price": 1.77,
    "change": 0.15
  },
  {
    "ticker": "GLD",
    "name": "Absa NewGold ETF",
    "volume": "430.0",
    "price": 5000.0,
    "change": 195.0
  },
  {
    "ticker": "HAFR",
    "name": "Home Afrika Limited",
    "volume": "416476.0",
    "price": 1.15,
    "change": -0.04
  },
  {
    "ticker": "HBE",
    "name": "Homeboyz Entertainment",
    "volume": "",
    "price": 4.66,
    "change": NaN
  },
  {
    "ticker": "HFCK",
    "name": "HF Group Limited",
    "volume": "191285.0",
    "price": 10.65,
    "change": 0.05
  },
  {
    "ticker": "IMH",
    "name": "I&M Holdings Plc",
    "volume": "19708.0",
    "price": 43.95,
    "change": 0.2
  },
  {
    "ticker": "JUB",
    "name": "Jubilee Holdings Limited",
    "volume": "2171.0",
    "price": 317.0,
    "change": -3.0
  },
  {
    "ticker": "KAPC",
    "name": "Kapchorua Tea Company Limited",
    "volume": "629.0",
    "price": 231.0,
    "change": 9.0
  },
  {
    "ticker": "KCB",
    "name": "KCB Group",
    "volume": "2044282.0",
    "price": 60.5,
    "change": 1.75
  },
  {
    "ticker": "KEGN",
    "name": "KenGen Plc",
    "volume": "2518376.0",
    "price": 10.05,
    "change": 0.05
  },
  {
    "ticker": "KNRE",
    "name": "Kenya Re-Insurance Corporation Ltd",
    "volume": "2894832.0",
    "price": 3.0,
    "change": 0.01
  },
  {
    "ticker": "KPLC",
    "name": "Kenya Power & Lighting Company",
    "volume": "620814.0",
    "price": 13.35,
    "change": 0.05
  },
  {
    "ticker": "KPLC-P4",
    "name": "Kenya Power 4% Preference Shares",
    "volume": "",
    "price": 4.51,
    "change": NaN
  },
  {
    "ticker": "KPLC-P7",
    "name": "Kenya Power 7% Preference Shares",
    "volume": "",
    "price": 6.0,
    "change": NaN
  },
  {
    "ticker": "KQ",
    "name": "Kenya Airways Limited",
    "volume": "246449.0",
    "price": 3.79,
    "change": 0.03
  },
  {
    "ticker": "KUKZ",
    "name": "Kakuzi Limited",
    "volume": "286.0",
    "price": 415.0,
    "change": -10.0
  },
  {
    "ticker": "KURV",
    "name": "Kurwitu Ventures Limited",
    "volume": "",
    "price": 1500.0,
    "change": NaN
  },
  {
    "ticker": "LAPR",
    "name": "Laptrust Imara Income-REIT",
    "volume": "",
    "price": 20.0,
    "change": NaN
  },
  {
    "ticker": "LBTY",
    "name": "Liberty Kenya Holdings Limited",
    "volume": "1004407.0",
    "price": 10.5,
    "change": -0.35
  },
  {
    "ticker": "LIMT",
    "name": "Limuru Tea Company Limited",
    "volume": "",
    "price": 375.0,
    "change": NaN
  },
  {
    "ticker": "LKL",
    "name": "Longhorn Publishers Limited",
    "volume": "1112.0",
    "price": 3.0,
    "change": 0.02
  },
  {
    "ticker": "MSC",
    "name": "Mumias Sugar Company Limited",
    "volume": "",
    "price": 0.28,
    "change": NaN
  },
  {
    "ticker": "NBV",
    "name": "Nairobi Business Ventures Ltd",
    "volume": "70708.0",
    "price": 1.6,
    "change": 0.04
  },
  {
    "ticker": "NCBA",
    "name": "NCBA Group Plc",
    "volume": "60909.0",
    "price": 82.0,
    "change": -3.5
  },
  {
    "ticker": "NMG",
    "name": "Nation Media Group",
    "volume": "2948.0",
    "price": 13.4,
    "change": -0.2
  },
  {
    "ticker": "NSE",
    "name": "Nairobi Securities Exchange Limited",
    "volume": "68353.0",
    "price": 15.2,
    "change": 0.2
  },
  {
    "ticker": "OCH",
    "name": "Olympia Capital Holdings Limited",
    "volume": "12245.0",
    "price": 7.1,
    "change": -0.3
  },
  {
    "ticker": "PORT",
    "name": "East African Portland Cement Co. Ltd",
    "volume": "55.0",
    "price": 60.0,
    "change": 0.0
  },
  {
    "ticker": "SASN",
    "name": "Sasini Tea and Coffee Limited",
    "volume": "18896.0",
    "price": 18.7,
    "change": 0.1
  },
  {
    "ticker": "SBIC",
    "name": "Stanbic Holdings Limited",
    "volume": "46673.0",
    "price": 197.5,
    "change": -0.5
  },
  {
    "ticker": "SCAN",
    "name": "ScanGroup Limited",
    "volume": "13797.0",
    "price": 2.85,
    "change": -0.03
  },
  {
    "ticker": "SCBK",
    "name": "Standard Chartered Bank Limited",
    "volume": "3519.0",
    "price": 302.5,
    "change": 0.5
  },
  {
    "ticker": "SCOM",
    "name": "Safaricom Plc",
    "volume": "2726781.0",
    "price": 29.25,
    "change": -0.25
  },
  {
    "ticker": "SGL",
    "name": "Standard Group Limited",
    "volume": "1770.0",
    "price": 6.0,
    "change": -0.3
  },
  {
    "ticker": "SKL",
    "name": "Shri Krishana Overseas Ltd",
    "volume": "10002.0",
    "price": 8.16,
    "change": 0.0
  },
  {
    "ticker": "SLAM",
    "name": "Sanlam Kenya Plc",
    "volume": "28078.0",
    "price": 8.98,
    "change": 0.1
  },
  {
    "ticker": "SMER",
    "name": "Sameer Africa Plc",
    "volume": "85567.0",
    "price": 14.75,
    "change": 0.6
  },
  {
    "ticker": "SMWF",
    "name": "Satrix MSCI World Feeder ETF",
    "volume": "25.0",
    "price": 857.0,
    "change": 0.0
  },
  {
    "ticker": "TCL",
    "name": "Trans Century Limited",
    "volume": "",
    "price": 0.71,
    "change": NaN
  },
  {
    "ticker": "TOTL",
    "name": "Total Kenya Limited",
    "volume": "194054.0",
    "price": 47.0,
    "change": 3.0
  },
  {
    "ticker": "TPSE",
    "name": "TPS Eastern Africa Serena Limited",
    "volume": "22.0",
    "price": 17.6,
    "change": -0.25
  },
  {
    "ticker": "UCHM",
    "name": "Uchumi Supermarket Limited",
    "volume": "38526.0",
    "price": 0.38,
    "change": 0.01
  },
  {
    "ticker": "UMME",
    "name": "Umeme Limited",
    "volume": "43600.0",
    "price": 8.0,
    "change": -0.04
  },
  {
    "ticker": "UNGA",
    "name": "Unga Group Limited",
    "volume": "137.0",
    "price": 24.9,
    "change": 1.9
  },
  {
    "ticker": "WTK",
    "name": "Williamson Tea Kenya Limited",
    "volume": "2901.0",
    "price": 193.5,
    "change": 1.5
  },
  {
    "ticker": "XPRS",
    "name": "Express Kenya Limited",
    "volume": "15667.0",
    "price": 7.0,
    "change": 0.0
  }
]